{"Date": "2019-08-15 15:55:03", "content": "<p>\n</p> <p>\n</p> <p><span class=\"word-wrap-span\">TALK</span> <span class=\"word-wrap-span\">GROWS</span> ever-<span class=\"word-wrap-span\">louder</span> of <span class=\"word-wrap-span\">Britain</span> exiting the <span class=\"word-wrap-span\">European</span> <span class=\"word-wrap-span\">Union</span> without a   <span class=\"word-wrap-span\">divorce</span> agreement.   <span class=\"word-wrap-span\">Most</span> <span class=\"word-wrap-span\">parliamentarian</span>s would rather avoid that\u2014but can they do any<span class=\"word-wrap-span\">thin</span>g to stop it? We join a   <span class=\"word-wrap-span\">Ukrainian</span> military exercise   as the country seeks to beef up defences that were nearly wiped out by <span class=\"word-wrap-span\">Russia</span>\u2019s <span class=\"word-wrap-span\">annexation</span> of <span class=\"word-wrap-span\">Crimea</span>. <span class=\"word-wrap-span\">And</span>,  <span class=\"word-wrap-span\">China</span>\u2019s  tech companies train their <span class=\"word-wrap-span\">sigh</span>ts on the   tech-<span class=\"word-wrap-span\">savvy</span> <span class=\"word-wrap-span\">elderly</span>.  \n</p> <p>\n</p> <p> <span class=\"word-wrap-span\">Runtime</span>: 21 min\n</p> <p>\n</p> <p><span class=\"word-wrap-span\">Listen</span> on:  <span class=\"word-wrap-span\">Apple</span> Podcasts  |  Spotify  |  Google  |  <span class=\"word-wrap-span\">Stitcher</span>  |  TuneIn </p>", "Last": "2019_8_15_2.json", "Next": "2019_8_15_4.json", "assistent": {"And": {"ex": ["conj. \u548c\uff0c\u4e0e\uff1b\u5c31\uff1b\u800c\u4e14\uff1b\u4f46\u662f\uff1b\u7136\u540e", "n. (And)\u4eba\u540d\uff1b(\u571f\u3001\u745e\u5178)\u5b89\u5fb7"], "pron": {"peg": "[\u0259nd, \u0259n,\u00e6nd]", "pam": "[\u0259nd, \u0259n,\u00e6nd]"}, "st": {}, "wp": {}, "eg2": []}, "Apple": {"ex": ["n. \u82f9\u679c\u516c\u53f8\uff1b\u3010\u690d\u3011\u82f9\u679c\uff1b\u3010\u690d\u3011\u82f9\u679c\u6811", "\u7f51\u7edc \u82f9\u679c\u7535\u8111\uff1b\u7f8e\u56fd\u82f9\u679c\uff1b\u7f8e\u56fd\u82f9\u679c\u516c\u53f8"], "pron": {"peg": "\u82f1\u00a0['\u00e6pl] ", "pam": "\u7f8e\u00a0[\u02c8\u00e6p(\u0259)l] "}, "eg2": [["an apple pie", "\u82f9\u679c\u9985\u997c"], ["apple sauce", "\u82f9\u679c\u6c99\u53f8"], ["a garden with three apple trees", "\u6709\u4e09\u68f5\u82f9\u679c\u6811\u7684\u82b1\u56ed"], ["They really are apples and oranges.", "\u4ed6\u4eec\u786e\u5b9e\u662f\u8fe5\u7136\u4e0d\u540c\u3002"], ["They are both great but you can't compare apples and oranges .", "\u4ed6\u4eec\u4fe9\u90fd\u5f88\u68d2\uff0c\u4f46\u662f\u622a\u7136\u4e0d\u540c\uff0c\u65e0\u6cd5\u6bd4\u8f83\u3002"], ["They really are apples and oranges.", "\u4ed6\u4eec\u786e\u5b9e\u662f\u8fe5\u7136\u4e0d\u540c\u3002"], ["They are both great but you can't compare apples and oranges .", "\u4ed6\u4eec\u4fe9\u90fd\u5f88\u68d2\uff0c\u4f46\u662f\u622a\u7136\u4e0d\u540c\uff0c\u65e0\u6cd5\u6bd4\u8f83\u3002"]]}, "Boris": {"ex": ["n. \u9c8d\u91cc\u65af\uff08\u7537\u5b50\u540d\uff09"], "pron": {"peg": "['b\u0254ris]", "pam": "['b\u0254ris]"}, "st": {}, "wp": {"Boris Johnson": "\u9c8d\u91cc\u65af\u00b7\u7ea6\u7ff0\u900a;\u7ea6\u7ff0\u900a;\u9c8d\u91cc\u65af;\u4f26\u6566\u5e02\u957f\u5f3a\u751f", "Boris Godunov": "\u9c8d\u91cc\u65af\u00b7\u6208\u4e1c\u8bfa\u592b;\u9c8d\u5229\u65af\u00b7\u90ed\u591a\u8bfa\u592b;\u5531\u7247\u540d;\u90ed\u591a\u8bfa\u592b", "Boris Meissner": "\u9c8d\u91cc\u65af\u00b7\u8fc8\u65af\u7eb3", "Boris Vasilyev": "\u9c8d\u91cc\u65af\u00b7\u5229\u6c83\u7ef4\u5947\u00b7\u74e6\u897f\u91cc\u8036\u592b;\u9c8d\u91cc\u65af\u00b7\u74e6\u897f\u91cc\u8036\u592b", "Boris Polevoy": "\u6ce2\u5217\u4f0f\u4f9d", "Boris Klaiman": "\u514b\u83b1\u66fc", "Boris Fogel": "\u9c8d\u91cc\u65af\u00b7\u798f\u683c\u5c14", "Boris Morros": "\u9c8d\u91cc\u65af\u00b7\u83ab\u7f57\u65af", "Boris Legran": "\u9c8d\u91cc\u65af\u00b7\u83b1\u683c\u5170\u5fb7"}, "eg2": []}, "Britain": {"ex": ["n. \u82f1\u56fd\uff1b\u4e0d\u5217\u98a0"], "pron": {"peg": "['br\u026atn]", "pam": "['br\u026atn]"}, "st": {}, "wp": {}, "eg2": []}, "China": {"ex": ["n. \u4e2d\u56fd", "adj. \u4e2d\u56fd\u7684\uff1b\u4e2d\u56fd\u5236\u9020\u7684", "n. (china) \u74f7\u5668", "adj. (china) \u74f7\u5236\u7684"], "pron": {"peg": "[\u02c8t\u0283a\u026an\u0259]", "pam": "[\u02c8t\u0283a\u026an\u0259]"}, "st": {}, "wp": {}, "eg2": []}, "Crimea": {"ex": ["n. \u514b\u91cc\u7c73\u4e9a(\u534a\u5c9b)\uff1b\u514b\u91cc\u6728(\u534a\u5c9b)", "\u7f51\u7edc \u514b\u91cc\u7c73\u4e9a\u534a\u5c9b\uff1b\u514b\u91cc\u7c73\u4e9a\u5730\u533a\uff1b\u917f\u9020\u5382\u4f4d\u4e8e\u514b\u91cc\u7c73\u5c14"], "pron": {"peg": "\u82f1\u00a0[krai\u02c8mi\u0259] ", "pam": "\u7f8e\u00a0[kra\u026a\u02c8mi\u0259] "}, "eg2": []}, "European": {"ex": ["n. \u6b27\u6d32\u4eba\uff1b\u7956\u7c4d\u6b27\u6d32\u7684\u4eba\uff1b\u6b27\u6d32\u4eba\u7684\u540e\u88d4\uff1b\u6b27\u76df\u652f\u6301\u8005", "adj. \u6b27\u6d32\u7684\uff1b\u5168\u6b27\u7684\uff1b\u6b27\u76df\u7684", "\u7f51\u7edc \u6b27\u5f0f\uff1b\u6b27\u5f0f\u8f66"], "pron": {"peg": "\u82f1\u00a0[.j\u028a\u0259r\u0259'pi\u02d0\u0259n] ", "pam": "\u7f8e\u00a0[.j\u028ar\u0259'pi\u0259n] "}, "eg2": [["European languages", "\u6b27\u6d32\u7684\u8bed\u8a00"], ["European law", "\u6b27\u76df\u7684\u6cd5\u5f8b"], ["our European partners", "\u6211\u4eec\u7684\u6b27\u76df\u4f19\u4f34"], ["a good European", "\u6b27\u76df\u7684\u575a\u5b9a\u62e5\u62a4\u8005"]]}, "GROWS": {"ex": ["\u79cd\u690d"], "pron": {}, "st": {}, "wp": {}, "eg2": []}, "Johnson": {"ex": ["n. \u7ea6\u7ff0\u900a\uff08\u59d3\u6c0f\uff09"], "pron": {"peg": "['d\u0292\u0252ns(\u0259)n]", "pam": "['d\u0292\u0252ns(\u0259)n]"}, "st": {}, "wp": {"Dwayne Johnson": "\u5de8\u77f3\u5f3a\u68ee;\u9053\u6069\u00b7\u5f3a\u68ee;\u7ea6\u7ff0\u900a;\u5fb7\u5a01\u6069\u00b7\u7ea6\u7ff0\u900a", "Samuel Johnson": "\u585e\u7f2a\u5c14\u00b7\u7ea6\u7ff0\u900a;\u7ea6\u7ff0\u900a;\u585e\u7f2a\u5c14\u7ea6\u7ff0\u900a;\u7ea6\u7ff0\u751f", "Kevin Johnson": "\u51ef\u6587\u00b7\u7ea6\u7ff0\u900a;\u7ea6\u7ff0\u900a;\u51ef\u6587;\u51ef\u6587\u7ea6\u7ff0\u900a", "Larry Johnson": "\u62c9\u91cc\u00b7\u7ea6\u7ff0\u900a;\u62c9\u91cc;\u62c9\u91cc\u7ea6\u7ff0\u900a", "Allen Johnson": "\u963f\u5170\u00b7\u7ea6\u7ff0\u900a;\u7ea6\u7ff0\u900a;\u963f\u5170\u7ea6\u7ff0\u900a", "Johnson Controls": "\u6c5f\u68ee\u81ea\u63a7;\u6c5f\u68ee\u81ea\u63a7\u516c\u53f8;\u6c5f\u68ee\u81ea\u63a7\u6709\u9650\u516c\u53f8", "Aaron Johnson": "\u4e9a\u4f26\u00b7\u5f3a\u68ee;\u7ea6\u7ff0\u900a;\u4e9a\u4f26\u00b7\u7ea6\u7ff0\u900a;\u827e\u4f26\u5e84\u900a", "Roger Johnson": "\u7f57\u6770\u00b7\u7ea6\u7ff0\u900a;\u7ea6\u7ff0\u900a;\u590f\u5929\u52a0\u76df\u7684\u4e2d\u536b\u5e84\u900a;\u7f57\u683c\u00b7\u7ea6\u7ff0\u68ee", "Rian Johnson": "\u83b1\u6069\u00b7\u7ea6\u7ff0\u900a;\u7ea6\u7ff0\u900a;\u83b1\u6069\u5c0a\u900a;\u5bfc\u6f14"}, "eg2": []}, "Listen": {"ex": ["vi. \u542c\uff0c\u503e\u542c\uff1b\u542c\u4ece\uff0c\u542c\u4fe1", "n. \u542c\uff0c\u503e\u542c"], "pron": {"peg": "['l\u026asn]", "pam": "['l\u026asn]"}, "st": {}, "wp": {"listen into": "\u76d1\u542c;\u5077\u542c;\u542c\u5e7f\u64ad", "listen to": "\u542c;\u503e\u542c;\u542c\u67d0\u4eba\u8bb2\u8bdd;\u542c\u53d6", "listen for": "\u7b49\u7740\u542c;\u7559\u795e\u542c;\u503e\u542c;\u4e3b\u52a8\u542c", "Please listen": "\u8981\u542c\u8bdd;\u8bf7\u4f60\u6ce8\u610f\u542c;\u4f60\u542c\u6211\u8bf4;\u503e\u542c", "Carefully listen": "\u4ed4\u7ec6\u542c;\u4ed4\u7ec6\u542c\u8bb2;\u4ed4\u7ec6\u542c\u8bfe;\u8ba4\u771f\u542c\u8bfe", "Listen girl": "\u542c\u7740;\u542c\u5973\u5b69;\u542c\u5973\u7ae5;\u542c\u7740\u5973\u5b69", "Listen Port": "\u76d1\u542c\u7aef\u53e3", "listen in": "\u76d1\u542c;\u4e2d\u5b66\u82f1\u8bed\u542c\u529b\u6559\u7a0b;\u6536\u542c", "listen interval": "\u542c\u95f4\u9694;\u8046\u542c\u95f4\u9694;\u5b57\u6bb5"}, "eg2": []}, "Most": {"ex": ["adv. \u6700\uff1b\u975e\u5e38\uff0c\u6781\u5176\uff1b\u6700\u591a\uff1b\u51e0\u4e4e", "adj. \u5927\u90e8\u5206\u7684\uff0c\u591a\u6570\u7684\uff1b\u6700\u591a\u7684", "n. \u5927\u90e8\u5206\uff0c\u5927\u591a\u6570", "n. (Most)\u4eba\u540d\uff1b(\u5fb7\u3001\u4fc4\u3001\u6cd5\u3001\u82ac\u3001\u6377\u3001\u82f1)\u83ab\u65af\u7279"], "pron": {"peg": "[most]", "pam": "[most]"}, "st": {}, "wp": {"most likely": "\u5927\u6982;\u4e5f\u8bb8;\u5f88\u53ef\u80fd", "most recent": "\u6700\u8fd1\u7684;\u6700\u65b0\u52a8\u6001;\u6700\u65b0\u4fe1\u606f;\u6700\u65b0", "most viewed": "\u6d4f\u89c8\u6700\u591a\u7684\u6587\u7ae0;\u6700\u591a\u4eba\u770b\u8fc7\u7684;\u6700\u53d7\u6b22\u8fce;\u5927\u90e8\u5206\u4eba\u6c14", "most importantly": "\u6700\u91cd\u8981\u7684\u662f;\u6700\u4e3a\u91cd\u8981;\u6700\u91cd\u8981;\u6700\u4e3a\u91cd\u8981\u7684\u662f", "most formal": "\u6b63\u793c\u88c5", "most frequent": "\u4e3b\u8981\u7684\u6700\u7ecf\u5e38\u7684;\u6700\u5e38\u89c1\u7684;\u6700\u7ecf\u5e38\u7684", "Most unimaginated": "\u6700\u65e0\u6cd5\u60f3\u8c61\u7684", "most high": "\u5177\u6709\u81f3\u9ad8;\u81f3\u9ad8\u8005", "most inspiration": "\u6700\u4f73\u8868\u73b0"}, "eg2": []}, "Runtime": {"ex": ["n. \u6267\u884c\u65f6\u95f4\uff0c\u8fd0\u884c\u65f6\u95f4"], "pron": {"peg": "['r\u028cnta\u026am]", "pam": "['r\u028cnta\u026am]"}, "st": {}, "wp": {"runtime environment": "\u8fd0\u884c\u73af\u5883;\u8fd0\u884c\u65f6\u73af\u5883;\u884c\u73af\u5883;\u73af\u5883", "runtime error": "\u8fd0\u884c\u65f6\u51fa\u9519;\u8fd0\u884c\u65f6\u9519\u8bef;\u8fd0\u884c\u65f6\u95f4\u9519\u8bef;\u8fd0\u8f6c\u65f6\u51fa\u9519", "Concurrency Runtime": "\u5e76\u53d1\u8fd0\u884c\u65f6", "Common Runtime": "\u516c\u5171\u8fd0\u884c\u65f6;\u8bed\u8a00\u548c\u901a\u7528\u8fd0\u884c\u65f6;\u516c\u5171\u8fd0\u884c\u73af\u5883;\u8fd0\u884c\u5e93", "Runtime Database": "\u8fd0\u884c\u65f6\u6570\u636e\u5e93;\u8fd0\u884c\u6570\u636e\u5e93;\u5206\u5e03\u5f0f\u52a8\u6001\u6570\u636e\u5e93", "Captive Runtime": "\u8fd0\u884c\u65f6\u7ed1\u5b9a", "Runtime License": "\u8bb8\u53ef\u6388\u6743;\u8fd0\u884c\u8bb8\u53ef", "runtime host": "\u8fd0\u884c\u65f6\u4e3b\u673a;\u6267\u884c\u9636\u6bb5\u4e3b\u673a;\u5e93\u5bbf\u4e3b", "Reports Runtime": "\u4e0d\u6307\u5b9a\u62a5\u8868\u540d\u800c\u6253\u5f00;\u62a5\u8868\u8fd0\u884c\u5668"}, "eg2": []}, "Russia": {"ex": ["n. \u4fc4\u7f57\u65af\u8054\u90a6\uff1b\u4fc4\u56fd\uff1b\u3010\u56fd\u3011\u4fc4\u7f57\u65af\uff1b(\u73b0\u4eca\u7684)\u4fc4\u7f57\u65af\u8054\u90a6", "\u7f51\u7edc \u82cf\u4fc4\uff1b\u82cf\u8054"], "pron": {"peg": "\u82f1\u00a0['r\u028c\u0283\u0259] ", "pam": "\u7f8e\u00a0['r\u028c\u0283\u0259] "}, "eg2": []}, "Stitcher": {"ex": ["n. \u3014\u673a\u3015\u7f1d\u9488\uff1b\u62fc\u9022\u673a\uff1b\u9489\u7bb1\u673a\uff1b\u9f7f\u5f62\u538b\u6eda", "\u7f51\u7edc \u5e26\u6750\u7f1d\u5408\u673a\uff1b\u9489\u4e66\u673a\uff1b\u8ba2\u4e66\u673a"], "pron": {"peg": "\u82f1\u00a0['st\u026at\u0283\u0259] ", "pam": "\u7f8e\u00a0['st\u026at\u0283\u0259] "}, "eg2": []}, "TALK": {"ex": ["v. \u8bf4\u8bdd\uff1b\u8c08\u8bba\uff1b\u8c08\u5fc3\uff1b\u8c08\u5224\uff1b\uff08\u7528\u67d0\u79cd\u8bed\u8a00\uff09\u8bb2\uff1b\u8bf4\u670d\uff1b\u6cc4\u9732\u79d8\u5bc6\uff1b\u8bae\u8bba\uff1b\u8bb2\u7684\u662f\uff1b\u8bf4\u95f2\u8bdd\uff1b\u4f9b\u51fa\u6d88\u606f", "n. \u8c08\u8bdd\uff1b\u8c08\u5224\uff1b\uff08\u975e\u6b63\u5f0f\u7684\uff09\u8bb2\u8bdd\uff1b\u62a5\u544a\uff1b\u7a7a\u8c08\uff1b\u8c23\u8a00\uff1b\u8bdd\u9898\uff1b\u8bf4\u8bdd\u7684\u65b9\u5f0f"], "pron": {"peg": "[t\u0254k]", "pam": "[t\u0254k]"}, "st": {}, "wp": {"Pillow Talk": "\u6795\u8fb9\u7ec6\u8bed;\u518d\u89c1\u5355\u4eba\u5e8a;\u6795\u8fb9\u6084\u6084\u8bdd;\u6795\u8fb9\u8bdd", "Talk Radio": "\u8131\u53e3\u79c0;\u8c08\u8bdd\u7535\u53f0;\u6293\u72c2\u7535\u53f0;\u6b7b\u4ea1\u70ed\u7ebf", "talk about": "\u8c08\u8bba;\u8bae\u8bba;\u8c08\u5230;\u8ba8\u8bba", "Dirty talk": "\u4e0b\u6d41\u8bdd;\u8bf4\u810f\u8bdd;\u54b8\u6e7f\u8bdd;\u661f\u9645\u5f69\u8679", "TALK ASIA": "\u4e9a\u6d32\u540d\u4eba\u804a\u5929\u5ba4;\u5bf9\u8bdd\u4e9a\u6d32;\u4e9a\u6d32\u8bbf\u8c08;\u4e9a\u6d32\u540d\u6d41\u8c08\u5929\u5ba4", "free talk": "\u81ea\u7531\u4ea4\u8c08;\u81ea\u7531\u8c08\u8bdd;\u81ea\u7531\u8c08;\u81ea\u7531\u8ba8\u8bba", "Price talk": "\u5b9a\u4ef7\u8c08\u5224;\u5b9a\u4ef7\u6784\u548c", "talk to": "\u8d23\u5907;\u4e0e\u67d0\u4eba\u8c08\u8bdd;\u5bf9\u67d0\u4eba\u8c08\u8bdd;\u8ddf\u67d0\u4eba\u8c08\u8bdd", "Talk Only": "\u6df1\u60c5\u5bf9\u8bdd;\u53ea\u8bb2\u65b9\u5f0f;\u5149\u8bf4\u4e0d\u505a;\u6d45\u8c08"}, "eg2": []}, "Ukrainian": {"ex": ["adj. \u4e4c\u514b\u5170\u7684\uff1b\u4e4c\u514b\u5170\u4eba\u7684", "n. \u4e4c\u514b\u5170\u4eba\uff1b\u4e4c\u514b\u5170\u8bed"], "pron": {"peg": "[ju:'kreini\u0259n; -'krai-]", "pam": "[ju:'kreini\u0259n; -'krai-]"}, "st": {}, "wp": {"Ukrainian Cup": "\u4e4c\u514b\u5170\u676f", "Ukrainian SSR": "\u4e4c\u514b\u5170", "ukrainian winter": "\u4e4c\u51ac", "Ukrainian history": "\u4e4c\u514b\u5170\u5386\u53f2", "Ukrainian Nixon": "\u4e4c\u514b\u5170\u5c3c\u514b\u677e", "Ukrainian nation": "\u4e4c\u514b\u5170\u6c11\u65cf", "ukrainian rock": "\u6211\u559c\u6b22\u542c\u7684\u97f3\u4e50", "Ukrainian Dances": "\u5531\u7247\u540d", "ukrainian wikipedia": "\u4e4c\u514b\u5170\u8bed\u7ef4\u57fa\u767e\u79d1;\u514b\u57fa\u767e\u79d1"}, "eg2": []}, "Union": {"ex": ["n. \u8054\u76df\uff1b\u5de5\u4f1a\uff1b\u8054\u5408\uff1b\u8054\u5408\u4f1a", "\u7f51\u7edc \u5e76\u96c6\uff1b\u5408\u5e76\uff1b\u7ed3\u5408"], "pron": {"peg": "\u82f1\u00a0['ju\u02d0nj\u0259n] ", "pam": "\u7f8e\u00a0['junj\u0259n] "}, "eg2": [["I've joined the union .", "\u6211\u5df2\u7ecf\u52a0\u5165\u5de5\u4f1a\u3002"], ["a union member", "\u5de5\u4f1a\u4f1a\u5458"], ["the Scottish Rugby Union", "\u82cf\u683c\u5170\u6a44\u6984\u7403\u534f\u4f1a"], ["the former Soviet Union", "\u524d\u82cf\u7ef4\u57c3\u8054\u90a6"], ["the European Union", "\u6b27\u6d32\u8054\u76df"], ["the Union and the Confederacy", "\u5408\u4f17\u56fd\u4e0e\u5357\u90e8\u90a6\u8054"], ["the State of the Union address by the President", "\u7f8e\u56fd\u603b\u7edf\u5411\u56fd\u4f1a\u53d1\u8868\u7684\u56fd\u60c5\u54a8\u6587"], ["a summit to discuss economic and monetary union", "\u5546\u8ba8\u7ecf\u6d4e\u548c\u8d27\u5e01\u8054\u76df\u7684\u9ad8\u5cf0\u4f1a\u8bae"], ["Northern Ireland's union with Britain", "\u5317\u7231\u5c14\u5170\u540c\u82f1\u56fd\u7684\u8054\u5408"], ["sexual union", "\u6027\u7ed3\u5408"], ["Their union was blessed with six children.", "\u4ed6\u4eec\u5a5a\u540e\u5e78\u5f97\u516d\u4e2a\u513f\u5973\u3002"]]}, "annexation": {"ex": ["n. \u5408\u5e76\uff1b\u9644\u52a0\u7269"], "pron": {"peg": "[,\u00e6n\u025bk'se\u0283\u0259n]", "pam": "[,\u00e6n\u025bk'se\u0283\u0259n]"}, "st": {}, "wp": {"annexation of": "\u517c\u5e76\u4f5b\u7f57\u91cc\u8fbe", "multinational annexation": "\u8de8\u56fd\u5e76\u8d2d", "annexation loan": "\u5e76\u8d2d\u8d37\u6b3e", "annexation property": "\u4fb5\u541e\u8d22\u4ea7", "symbolic annexation": "\u8c61\u5f81\u5408\u5e76", "annexation and": "\u4f01\u4e1a\u517c\u5e76\u91cd\u7ec4", "transnational annexation": "\u8de8\u56fd\u5e76\u8d2d", "merger annexation": "\u517c\u5e76", "annexation n": "\u5408\u5e76"}, "eg2": [["Palestinians say such an<b> annexation</b> would effectively cut the West Bank in two.", "\u5df4\u52d2\u65af\u5766\u4eba\u5219\u8ba4\u4e3a\u8fd9\u6837\u7684\u5408\u5e76\u65e0\u7591\u5c06\u4f1a\u628a\u897f\u5cb8\u5730\u533a\u4e00\u5272\u4e3a\u4e8c\u3002"], ["While apologizing for the , Japan's government has not acknowledged the treaty was illegal - as many on the Korean peninsula contend.", "\u671d\u9c9c\u4eba\u6307\u51fa\u201c\u65e5\u97e9\u5408\u5e76\u6761\u7ea6\u201d\u662f\u975e\u6cd5\u7684\u3002 \u800c\u65e5\u672c\u653f\u5e9c\u867d\u7136\u5df2\u7ecf\u5c31\u541e\u5e76\u671d\u9c9c\u534a\u5c9b\u9053\u6b49\uff0c\u5374\u6ca1\u6709\u627f\u8ba4\u90a3\u4e00\u6761\u7ea6\u662f\u975e\u6cd5\u7684\u3002"], ["The publishers removed one part about India\u2019s  of Sikkim in 1975 because they thought it might upset India.", "\u51fa\u7248\u5546\u62bd\u6389\u4e86\u4e00\u4e2a\u6709\u5173\u5370\u5ea61975\u5e74\u541e\u5e76\u9521\u91d1\u7684\u7ae0\u8282\uff0c\u56e0\u4e3a\u8fd9\u6837\u7684\u5185\u5bb9\u4f1a\u4f7f\u611f\u5230\u4e0d\u5b89\u3002"]]}, "divorce": {"ex": ["vt. \u4f7f\u79bb\u5a5a\uff0c\u4f7f\u5206\u79bb\uff1b\u4e0e\u2026\u79bb\u5a5a", "n. \u79bb\u5a5a\uff1b\u5206\u79bb", "vi. \u79bb\u5a5a"], "pron": {"peg": "[d\u026a'v\u0254rs]", "pam": "[d\u026a'v\u0254rs]"}, "st": {"transform": [["vt.", "divorced,divorcing"]]}, "wp": {"divorce rate": "\u79bb\u5a5a\u7387", "Divorce proceedings": "\u79bb\u5a5a\u8bc9\u8bbc;\u7ffb\u8bd1", "divorce certificate": "\u79bb\u5a5a\u8bc1;\u79bb\u5a5a\u8bc1\u660e\u4e66;\u79bb\u5a5a\u8bc1\u4e66", "divorce settlement": "\u79bb\u5a5a\u534f\u8bae\u4e66;\u79bb\u5a5a\u534f\u8bae;\u79bb\u5a5a\u8d22\u4ea7\u534f\u8bae;\u79bb\u5a5a\u89e3\u51b3", "Velvet Divorce": "\u5929\u9e45\u7ed2\u5206\u79bb;\u5929\u9e45\u7ed2\u79bb\u5a5a", "early divorce": "\u5148\u671f\u79bb\u5a5a", "Uncontested Divorce": "\u534f\u8bae\u79bb\u5a5a;\u65e0\u4e89\u8bae\u79bb\u5a5a\u6216\u534f\u8bae\u79bb\u5a5a", "lightning divorce": "\u95ea\u79bb", "Divorce clustering": "\u79bb\u5a5a\u7fa4\u805a\u6548\u5e94"}, "eg2": [["Everyone remarked on her .", "\u4eba\u4eba\u90fd\u5728\u8bae\u8bba\u5979\u7684\u79bb\u5a5a\u3002"], ["She will tackle him over the .", "\u5979\u5c06\u548c\u4ed6\u5c31\u79bb\u5a5a\u95ee\u9898\u8fdb\u884c\u4ea4\u6d89\u3002"], ["The news of her<b> divorce</b> gradually rippled outwards.", "\u5979\u79bb\u5a5a\u7684\u6d88\u606f\u6e10\u6e10\u5411\u5916\u4f20\u5f00\u3002"]]}, "elderly": {"pron": {"peg": "['\u025bld\u025ali]", "pam": "['\u025bld\u025ali]"}, "wp": {"Elderly man": "\u8001\u7fc1;\u8001\u8005;\u8001\u5e74\u4eba", "Elderly rat": "\u8001\u5e74\u5927\u9f20", "Elderly schizophrenia": "\u8001\u5e74\u7cbe\u795e\u5206\u88c2\u75c7", "Elderly Commission": "\u5b89\u8001\u4e8b\u52a1\u59d4\u5458\u4f1a", "Elderly patients": "\u8001\u5e74\u60a3\u8005;\u9ad8\u9f84\u60a3\u8005;\u8001\u5e74\u4eba;\u9ad8\u9f84", "frail elderly": "\u4f53\u5f31\u957f\u8005;\u8001\u5e74\u4eba;\u8870\u5f31\u8001\u4eba;\u5df1\u5e74\u8fc8\u4f53\u5f31", "elderly services": "\u5b89\u8001\u670d\u52a1", "elderly diseases": "\u8001\u5e74\u75c5", "elderly approach": "\u8001\u4eba\u529e\u6cd5;\u8001\u4eba\u7684\u505a\u6cd5;\u8001\u4eba\u7684\u65b9\u6cd5"}, "ex": ["adj. \u4e0a\u4e86\u5e74\u7eaa\u7684\uff1b\u8fc7\u4e86\u4e2d\u5e74\u7684\uff1b\u7a0d\u8001\u7684"], "eg2": [["\"Animals are everything to a Tuareg, \" an<b> elderly</b> nomad once explained to me. \"We drink their milk, we eat their meat, we use their skin, we trade them.", "\u201c\u7272\u755c\u5bf9\u56fe\u963f\u683c\u96f7\u4eba\u6765\u8bf4\u5c31\u662f\u4e00\u5207\uff0c\u201d\u4e00\u4f4d\u5e74\u957f\u7684\u6e38\u7267\u6c11\u6709\u6b21\u5411\u6211\u89e3\u91ca\uff0c\u201c\u6211\u4eec\u559d\u5b83\u4eec\u7684\u5976\uff0c\u5403\u5b83\u4eec\u7684\u8089\uff0c\u4f7f\u7528\u5b83\u4eec\u7684\u76ae\u5e76\u4e70\u5356\u5b83\u4eec\u3002"], ["Wang, the<b> elderly</b> farmer, said his daughter and her friends track coffee prices on computers. \u201cWhen the price goes up, we know it immediately, \u201d he said.", "\u738b\u4e2d\u5b66\uff0c\u8fd9\u4e2a\u5e74\u8fc8\u7684\u519c\u6c11\u8bf4\uff0c\u4ed6\u5973\u513f\u548c\u5979\u7684\u670b\u53cb\u4eec\u5728\u8ba1\u7b97\u673a\u4e0a\u8ddf\u8e2a\u5496\u5561\u4ef7\u683c\uff0c\u201c\u5f53\u4ef7\u683c\u4e0a\u6da8\u662f\uff0c\u6211\u4eec\u7acb\u523b\u5c31\u80fd\u77e5\u9053\u3002\u201d"], ["The<b> elderly</b> usually don't have regrets for what we did\uff0cbut rather for things we did not do.", " \u5e74\u957f\u7684\u4eba\u4e00\u822c\u4e0d\u4f1a\u4e3a\u6211\u4eec\u6240\u505a\u7684\u4e8b\u800c\u540e\u6094\uff0c\u800c\u4f1a\u4e3a\u6211\u4eec\u6240\u6ca1\u6709\u505a\u7684\u4e8b\u540e\u6094\u3002"]], "st": {}}, "louder": {"ex": ["adv. \u5927\u58f0\u4e00\u70b9"], "pron": {"peg": "[la\u028ad\u0259]", "pam": "[la\u028ad\u0259]"}, "st": {"transform": [["adj.", "louder,loudest"]]}, "wp": {"SCREAM LOUDER": "\u5c16\u58f0\u6495\u558a;\u5927\u58f0\u5c16\u53eb", "PLEASE LOUDER": "\u8bf7\u5927\u58f0\u70b9;\u8bf7\u5927\u58f0\u5c55;\u8bf7\u9ad8\u6da8", "The louder": "\u5728\u5927\u58f0\u70b9", "get louder": "\u53d8\u54cd\u4eae", "Louder T": "\u540d\u79f0", "crying louder": "\u9ad8\u58f0\u7684\u557c\u54ed", "Nikki Louder": "\u8868\u6f14\u8005", "Goes Louder": "\u4e13\u8f91\u540d\u79f0", "But Louder": "\u4f46\u66f4\u54cd\u4eae"}, "eg2": [["Speak .; Speak in a loud voice.", "\u8bf4\u5f97\u5927\u58f0\u70b9\u3002"], ["Speak<b> louder</b> so that we can hear you.", "\u8bf4\u5927\u58f0\u70b9\uff0c\u90a3\u6837\u6211\u4eec\u5c31\u80fd\u542c\u89c1\u4f60\u4e86\u3002"], ["The only thing I would change, if I knew then what I know now, is to make that warning , because back in 1997-98 nobody listened.", "\u5982\u679c\u6211\u4ee5\u524d\u77e5\u9053\u73b0\u5728\u6240\u77e5\u9053\u7684\u4e1c\u897f\uff0c\u90a3\u4e48\u6211\u8981\u4fee\u6539\u7684\u552f\u4e00\u7684\u4e1c\u897f\u662f\u4f7f\u8b66\u544a\u66f4\u5927\u58f0\u4e00\u70b9\uff0c\u56e0\u4e3a\u5728 1997 - 98 \u5e74\uff0c\u6ca1\u6709\u4eba\u4f1a\u542c\u8fdb\u8fd9\u4e9b\u8b66\u544a\u3002"]]}, "parliamentarian": {"pron": {"peg": "['p\u0251rl\u0259m\u0259n't\u025br\u026a\u0259n]", "pam": "['p\u0251rl\u0259m\u0259n't\u025br\u026a\u0259n]"}, "wp": {"fifth asian parliamentarian meeting": "\u7b2c\u4e94\u6b21\u4e9a\u6d32\u8bae\u5458\u4f1a\u8bae", "Parliamentarian democracy": "\u8bae\u4f1a\u5236", "A French Parliamentarian": "\u6cd5\u56fd\u8bae\u4f1a\u8bae\u5458", "Parliamentarian Chinese": "\u56fd\u4f1a\u8bae\u5458\u4e2d\u6587", "parliamentarian detail": "\u8bae\u4f1a\u8bae\u5458", "Arab Parliamentarian Information Network": "\u963f\u62c9\u4f2f\u8bae\u5458\u4fe1\u606f\u7f51", "Scottish parliamentarian": "\u82cf\u683c\u5170\u8bae\u4f1a", "parliamentarian parliamentary": "\u8bae\u4f1a\u7684", "parliamentarian Piquet": "\u52a0\u76df\u7f57\u4f2f\u7279"}, "ex": ["n. \u56fd\u4f1a\u8bae\u5458\uff0c\u719f\u7ec3\u800c\u53c8\u6709\u7ecf\u9a8c\u7684\u8bae\u5458", "adj. \u8bae\u4f1a\u7684"], "eg2": [[" Mabel Rebello, one of the new members, is not convinced that this time will be all that much different.", "\u56fd\u4f1a\u8bae\u5458\u6885\u5e03\u5c14\u00b7\u96f7\u8d1d\u7f57\u662f\u4f4d\u65b0\u6210\u5458\uff0c\u4f46\u5979\u4e0d\u76f8\u4fe1\u8fd9\u6b21\u548c\u4ee5\u5f80\u6709\u4f55\u4e0d\u540c\u3002"]], "st": {}}, "savvy": {"pron": {"peg": "['s\u00e6vi]", "pam": "['s\u00e6vi]"}, "wp": {}, "ex": ["n. \u609f\u6027\uff1b\u7406\u89e3\u80fd\u529b\uff1b\u61c2\u884c\uff08\u7684\u4eba\uff09", "vt. \u7406\u89e3\uff1b\u61c2", "vi. \u7406\u89e3\uff1b\u77e5\u9053"], "eg2": [["Tony's coming, do you ?", "\u6258\u5c3c\u6765\u4e86\uff0c\u4f60\u77e5\u9053\u5417?"], ["The one exception, he noted, was when he performed the experiment with a math- audience.", "\u4ed6\u53d1\u73b0\uff0c\u4f46\u6709\u4e00\u4e2a\u4f8b\u5916\uff0c\u5373\u5f53\u4ed6\u548c\u4e00\u4e2a\u5f88\u61c2\u6570\u5b66\u7684\u89c2\u4f17\u505a\u8fd9\u4e2a\u5b9e\u9a8c\u7684\u65f6\u5019\u3002"], ["And if you\u2019re worrying that you won\u2019t have anything to ask, I heard a very socially<b> savvy</b> friend ask an acquaintance what fillings he liked most in his sandwiches.", "\u5982\u679c\u4f60\u62c5\u5fc3\u4f60\u6ca1\u6709\u4ec0\u4e48\u597d\u95ee\u7684\uff0c\u6211\u542c\u4e00\u4f4d\u5728\u793e\u4ea4\u65b9\u9762\u975e\u5e38\u6709\u609f\u6027\u7684\u670b\u53cb\u66fe\u95ee\u4ed6\u7684\u670b\u53cb\uff0c\u95ee\u4ed6\u6700\u559c\u6b22\u5728\u4e09\u660e\u6cbb\u91cc\u5939\u4ec0\u4e48\u3002"]], "st": {"transform": [["adj.", "savvier,savviest"], ["vt.", "savvier,savviest"]]}}, "sighs": {"ex": ["n. \u53f9\u606f\uff1b\u6807\u8bb0\uff08sigh\u7684\u590d\u6570\uff09"], "pron": {}, "st": {}, "wp": {"Pointless sighs": "\u65e0\u8c13\u7684\u53f9\u606f", "Phonetic Sighs": "\u58f0\u7b26\u7cfb\u7edf", "Gary Sighs": "\u52a0\u91cc\u8212\u4e00\u53e3\u6c14", "Pige sighs": "\u76ae\u54e5\u5401\u4e86\u4e00\u53e3\u6c14", "Three Sighs": "\u4e09\u58f0\u65e0\u5948", "She sighs": "\u5979\u611f\u53f9\u9053", "Elephant Sighs": "\u5927\u8c61\u7684\u53f9\u606f", "vital sighs": "\u751f\u547d\u7279\u5f81"}, "eg2": []}, "sits": {"ex": ["v. \u5750\uff08sit\u7684\u7b2c\u4e09\u4eba\u79f0\u5355\u6570\u5f62\u5f0f\uff09", "n. \u5750\uff08sit\u7684\u590d\u6570\uff09"], "pron": {}, "st": {}, "wp": {"sits around": "\u5750\u5728\u5468\u56f4;\u5750\u5728\u90a3\u91cc\u770b;\u5750\u5728", "Sits gentleman": "\u5750\u7684\u58eb", "Sits straight": "\u5750\u7aef\u6b63", "binding sits": "\u7ed3\u5408\u4f4d", "Sits Then": "\u5750\u4fbf", "Wall sits": "\u9760\u5899\u5750;\u76f4\u89d2\u5750\u5899", "active sits": "\u6d3b\u6027\u4f4d", "Buddy Sits": "\u5df4\u8fea\u5c31\u5750\u4e0b", "SITS bits": "\u5206\u949f"}, "eg2": []}, "thins": {"ex": ["\u8584"], "pron": {}, "st": {}, "wp": {}, "eg2": []}}, "Title": "\u201cHe thinks that going for no-deal is the best way to win an election\u201d\u2014Boris Johnson\u2019s Brexit plans\n", "paperStatistics": {"suggestedfocus": "18.0 Minutes", "wordsset": 76, "keywords": "Boris,Brexit,Johnson,economist,election,https,tech,www", "toughwords": 67, "allwords": 82, "title": "\u201cHe thinks that going for no-deal is the best way to win an election\u201d\u2014Boris Johnson\u2019s Brexit plans\n", "desc": "https://www.economist.com/sites/default/files/20190817_blm506_1.jpg\n", "img": "https://www.economist.com/sites/default/files/20190817_blm506_1.jpg\n", "date": "2019-08-15 15:55:03", "link": "2019_8_15_3.json"}}