{"Date": "2019-08-02 20:09:24", "content": "<p>\n</p> <p>\n</p> <p>AS <span class=\"word-wrap-span\">AID</span> <span class=\"word-wrap-span\">WORKERS</span> battle  the second-worst <span class=\"word-wrap-span\">outbreak</span> in history,  they face violence <span class=\"word-wrap-span\">And</span> <span class=\"word-wrap-span\">disbelief</span>. A history of conflict, <span class=\"word-wrap-span\">suspicion</span> of the rich world <span class=\"word-wrap-span\">And</span> wild <span class=\"word-wrap-span\">conspiracy</span> theories make fighting a difficult battle far harder. <span class=\"word-wrap-span\">Architect</span>s are tackling the dark, loud, <span class=\"word-wrap-span\">violent</span> nature of   jails   to make them more about <span class=\"word-wrap-span\">rehabilitation</span> than <span class=\"word-wrap-span\">retribution</span>. <span class=\"word-wrap-span\">And</span>, the increasingly absurd   language of job <span class=\"word-wrap-span\">advert</span>s.   <span class=\"word-wrap-span\">Runtime</span>: 20 min\n</p> <p>\n</p> <p><span class=\"word-wrap-span\">Listen</span> on:  <span class=\"word-wrap-span\">Apple</span> Podcasts  |  Spotify  |  Google  |  <span class=\"word-wrap-span\">Stitcher</span>  |  TuneIn </p>", "Last": "2019_8_1_12.json", "Next": "2019_8_2_2.json", "assistent": {"AID": {"ex": ["v. \u5e2e\u52a9\uff1b\u534f\u52a9\uff1b\u652f\u6301\uff1b\u63a5\u6d4e", "n. \u5e2e\u52a9\uff1b\u52a9\u624b\uff1b\u5de5\u5177\uff1b\u624b\u6bb5", "\u7f51\u7edc \u63f4\u52a9\uff1b\u6551\u62a4\uff1b\u8f85\u52a9\u5668\u5177"], "pron": {"peg": "\u82f1\u00a0[e\u026ad] ", "pam": "\u7f8e\u00a0[ed] "}, "eg2": [["economic/humanitarian/emergency aid", "\u7ecf\u6d4e\u2571\u4eba\u9053\u4e3b\u4e49\u2571\u7d27\u6025\u63f4\u52a9"], ["An extra \u00a310 million in foreign aid has been promised.", "\u989d\u5916\u7684 1 000 \u4e07\u82f1\u9551\u5916\u56fd\u63f4\u52a9\u6b3e\u9879\u5df2\u5f97\u5230\u4fdd\u8bc1\u3002"], ["aid agencies(= organizations that provide help)", "\u6551\u63f4\u673a\u6784"], ["medical aid programmes", "\u533b\u7597\u63f4\u52a9\u8ba1\u5212"], ["He was breathing only with the aid of a ventilator.", "\u4ed6\u53ea\u80fd\u9760\u547c\u5438\u5668\u547c\u5438\u3002"], ["This job would be impossible without the aid of a computer.", "\u8fd9\u9879\u5de5\u4f5c\u4e0d\u7528\u8ba1\u7b97\u673a\u662f\u4e0d\u884c\u7684\u3002"], ["One of the staff saw he was in difficulty and came to his aid(= helped him) .", "\u4e00\u540d\u5de5\u4f5c\u4eba\u5458\u89c1\u4ed6\u6709\u56f0\u96be\uff0c\u4fbf\u8fc7\u6765\u5e2e\u5fd9\u3002"], ["a hearing aid", "\u52a9\u542c\u5668"], ["Photos make useful teaching aids.", "\u7167\u7247\u53ef\u4ee5\u6210\u4e3a\u6709\u7528\u7684\u6559\u5177\u3002"], ["collecting money in aid of charity", "\u4e3a\u8d44\u52a9\u6148\u5584\u4e8b\u4e1a\u7684\u52df\u6350"], ["collecting money in aid of charity", "\u4e3a\u8d44\u52a9\u6148\u5584\u4e8b\u4e1a\u7684\u52df\u6350"], ["What's all this crying in aid of?", "\u8fd9\u54ed\u53eb\u58f0\u7a76\u7adf\u662f\u4e3a\u4ec0\u4e48\uff1f"], ["What's all this crying in aid of?", "\u8fd9\u54ed\u53eb\u58f0\u7a76\u7adf\u662f\u4e3a\u4ec0\u4e48\uff1f"], ["The new test should aid in the early detection of the disease.", "\u65b0\u7684\u5316\u9a8c\u5e94\u8be5\u6709\u52a9\u4e8e\u65e9\u65e9\u68c0\u67e5\u51fa\u8fd9\u79cd\u75be\u75c5\u3002"], ["This feature is designed to aid inexperienced users.", "\u8fd9\u4e2a\u7279\u8272\u88c5\u7f6e\u662f\u4e3a\u5e2e\u52a9\u6ca1\u6709\u7ecf\u9a8c\u7684\u7528\u6237\u800c\u8bbe\u8ba1\u7684\u3002"], ["Aided by heat and strong winds, the fire quickly spread.", "\u501f\u52a9\u9ad8\u6e29\u548c\u5927\u98ce\uff0c\u706b\u52bf\u8fc5\u901f\u8513\u5ef6\u3002"], ["They were accused of aiding his escape.", "\u4ed6\u4eec\u88ab\u63a7\u5e2e\u52a9\u4ed6\u9003\u8dd1\u3002"], ["They were accused of aiding him in his escape.", "\u4ed6\u4eec\u88ab\u63a7\u5e2e\u52a9\u4ed6\u9003\u8dd1\u3002"], ["Words will be displayed around the room to aid students with spelling.", "\u5355\u8bcd\u4f1a\u5f20\u8d34\u5728\u5ba4\u5185\u5404\u5904\u4ee5\u5e2e\u52a9\u5b66\u751f\u5b66\u4e60\u62fc\u5199\u3002"], ["She stands accused of aiding and abetting the crime.", "\u5979\u88ab\u63a7\u5e2e\u52a9\u548c\u6559\u5506\u72af\u7f6a\u3002"], ["She stands accused of aiding and abetting the crime.", "\u5979\u88ab\u63a7\u5e2e\u52a9\u548c\u6559\u5506\u72af\u7f6a\u3002"]]}, "And": {"ex": ["conj. \u548c\uff0c\u4e0e\uff1b\u5c31\uff1b\u800c\u4e14\uff1b\u4f46\u662f\uff1b\u7136\u540e", "n. (And)\u4eba\u540d\uff1b(\u571f\u3001\u745e\u5178)\u5b89\u5fb7"], "pron": {"peg": "[\u0259nd, \u0259n,\u00e6nd]", "pam": "[\u0259nd, \u0259n,\u00e6nd]"}, "st": {}, "wp": {}, "eg2": []}, "Apple": {"ex": ["n. \u82f9\u679c\u516c\u53f8\uff1b\u3010\u690d\u3011\u82f9\u679c\uff1b\u3010\u690d\u3011\u82f9\u679c\u6811", "\u7f51\u7edc \u82f9\u679c\u7535\u8111\uff1b\u7f8e\u56fd\u82f9\u679c\uff1b\u7f8e\u56fd\u82f9\u679c\u516c\u53f8"], "pron": {"peg": "\u82f1\u00a0['\u00e6pl] ", "pam": "\u7f8e\u00a0[\u02c8\u00e6p(\u0259)l] "}, "eg2": [["an apple pie", "\u82f9\u679c\u9985\u997c"], ["apple sauce", "\u82f9\u679c\u6c99\u53f8"], ["a garden with three apple trees", "\u6709\u4e09\u68f5\u82f9\u679c\u6811\u7684\u82b1\u56ed"], ["They really are apples and oranges.", "\u4ed6\u4eec\u786e\u5b9e\u662f\u8fe5\u7136\u4e0d\u540c\u3002"], ["They are both great but you can't compare apples and oranges .", "\u4ed6\u4eec\u4fe9\u90fd\u5f88\u68d2\uff0c\u4f46\u662f\u622a\u7136\u4e0d\u540c\uff0c\u65e0\u6cd5\u6bd4\u8f83\u3002"], ["They really are apples and oranges.", "\u4ed6\u4eec\u786e\u5b9e\u662f\u8fe5\u7136\u4e0d\u540c\u3002"], ["They are both great but you can't compare apples and oranges .", "\u4ed6\u4eec\u4fe9\u90fd\u5f88\u68d2\uff0c\u4f46\u662f\u622a\u7136\u4e0d\u540c\uff0c\u65e0\u6cd5\u6bd4\u8f83\u3002"]]}, "Architect": {"ex": ["n. \u5efa\u7b51\u5e08\uff1b\u8bbe\u8ba1\u5e08\uff1b\u7f14\u9020\u8005\uff1b\u521b\u9020\u8005", "\u7f51\u7edc \u67b6\u6784\u5e08\uff1b\u5efa\u7b51\u8bbe\u8ba1\u5e08\uff1b\u5efa\u7b51\u5de5\u7a0b\u5e08"], "pron": {"peg": "\u82f1\u00a0['\u0251\u02d0(r)k\u026a.tekt] ", "pam": "\u7f8e\u00a0['\u0251rk\u026a.tekt] "}, "eg2": [["He was one of the principal architects of the revolution.", "\u4ed6\u662f\u90a3\u6b21\u9769\u547d\u7684\u4e3b\u8981\u53d1\u52a8\u8005\u4e4b\u4e00\u3002"], ["Jones was the architect of the team's first goal.", "\u743c\u65af\u7b56\u52a8\u7403\u961f\u653b\u5165\u7b2c\u4e00\u7403\u3002"]]}, "Congo": {"ex": ["n. \u521a\u679c\uff1b\u521a\u679c\u5171\u548c\u56fd\uff1b\u3010\u56fd\u3011\u521a\u679c\uff1b\u521a\u679c\u5e03", "\u7f51\u7edc \u521a\u679c\u60ca\u9b42\uff1b\u521a\u679c\u6c11\u4e3b\u5171\u548c\u56fd\uff1b\u521a\u679c\u6cb3"], "pron": {"peg": "\u82f1\u00a0['k\u0252\u014b\u0261\u0259\u028a] ", "pam": "\u7f8e\u00a0"}, "eg2": []}, "Ebola": {"ex": ["n. \u4f0a\u6ce2\u62c9\u75c5\u6bd2\uff1b\u57c3\u535a\u62c9\u75c5\u6bd2", "\u7f51\u7edc \u57c3\u6ce2\u62c9\uff1b\u57c3\u535a\u62c9\u51fa\u8840\u70ed\uff1b\u75c5\u6bd2\u4f0a\u6ce2\u62c9"], "pron": {"peg": "\u82f1\u00a0[i'b\u0259ul\u0259] ", "pam": "\u7f8e\u00a0[i\u02c8bo\u028al\u0259] "}, "eg2": []}, "Half": {"ex": ["n. \u4e00\u534a\uff1b\u534a\u573a\uff1b\u534a\u5b66\u5e74", "adv. \u4e00\u534a\u5730\uff1b\u90e8\u5206\u5730", "adj. \u4e00\u534a\u7684\uff1b\u4e0d\u5b8c\u5168\u7684\uff1b\u534a\u9014\u7684", "n. (Half)\u4eba\u540d\uff1b(\u963f\u62c9\u4f2f)\u54c8\u52d2\u592b\uff1b(\u5fb7)\u54c8\u5c14\u592b\uff1b(\u82f1)\u54c8\u592b"], "pron": {"peg": "[h\u00e6f]", "pam": "[h\u00e6f]"}, "st": {}, "wp": {"half time": "\u4e2d\u573a\u4f11\u606f;\u5b88\u95e8\u5458\u6280\u672f\u4e0e\u57fa\u672c\u8bad\u7ec3;\u534a\u671f;\u4eba\u751f\u4e0b\u534a\u573a", "One half": "\u4e00\u534a;\u4e8c\u5206\u4e4b\u4e00;\u4e00\u4eba\u4e00\u534a;\u6d6a\u5ba2\u5251\u5fc3", "half back": "\u524d\u536b;\u98de\u6251\u4f20\u7403;\u4e2d\u536b;\u534a\u80cc\u5bbd", "half leather": "\u534a\u76ae\u9762\u88c5\u8ba2;\u534a\u9769\u88c5;\u534a\u8868\u76ae\u88c5\u8ba2;\u534a\u76ae", "A half": "\u4e00\u5927\u534a;\u4e00\u534a;\u4e8c\u5206\u4e4b\u4e00;\u4ec0\u4e48\u90fd\u53ef\u4ee5", "half period": "\u534a\u5468\u671f;\u534a\u8870\u671f;\u534a\u5468\u671f\u534a\u8870\u671f;\u534a\u5bff\u671f", "Half Steel": "\u94a2\u6027\u751f\u94c1;\u534a\u94a2", "Robert Half": "\u82f1\u56fd\u4f5c\u5bb6\u54c8\u592b;\u52c3\u6d77\u4f5b;\u7f57\u81f4\u6052\u5bcc\u516c\u53f8", "half mirror": "\u534a\u53cd\u5c04\u955c;\u534a\u900f\u73ab;\u9b54\u672f\u955c"}, "eg2": []}, "Listen": {"ex": ["vi. \u542c\uff0c\u503e\u542c\uff1b\u542c\u4ece\uff0c\u542c\u4fe1", "n. \u542c\uff0c\u503e\u542c"], "pron": {"peg": "['l\u026asn]", "pam": "['l\u026asn]"}, "st": {}, "wp": {"listen into": "\u76d1\u542c;\u5077\u542c;\u542c\u5e7f\u64ad", "listen to": "\u542c;\u503e\u542c;\u542c\u67d0\u4eba\u8bb2\u8bdd;\u542c\u53d6", "listen for": "\u7b49\u7740\u542c;\u7559\u795e\u542c;\u503e\u542c;\u4e3b\u52a8\u542c", "Please listen": "\u8981\u542c\u8bdd;\u8bf7\u4f60\u6ce8\u610f\u542c;\u4f60\u542c\u6211\u8bf4;\u503e\u542c", "Carefully listen": "\u4ed4\u7ec6\u542c;\u4ed4\u7ec6\u542c\u8bb2;\u4ed4\u7ec6\u542c\u8bfe;\u8ba4\u771f\u542c\u8bfe", "Listen girl": "\u542c\u7740;\u542c\u5973\u5b69;\u542c\u5973\u7ae5;\u542c\u7740\u5973\u5b69", "Listen Port": "\u76d1\u542c\u7aef\u53e3", "listen in": "\u76d1\u542c;\u4e2d\u5b66\u82f1\u8bed\u542c\u529b\u6559\u7a0b;\u6536\u542c", "listen interval": "\u542c\u95f4\u9694;\u8046\u542c\u95f4\u9694;\u5b57\u6bb5"}, "eg2": []}, "Runtime": {"ex": ["n. \u6267\u884c\u65f6\u95f4\uff0c\u8fd0\u884c\u65f6\u95f4"], "pron": {"peg": "['r\u028cnta\u026am]", "pam": "['r\u028cnta\u026am]"}, "st": {}, "wp": {"runtime environment": "\u8fd0\u884c\u73af\u5883;\u8fd0\u884c\u65f6\u73af\u5883;\u884c\u73af\u5883;\u73af\u5883", "runtime error": "\u8fd0\u884c\u65f6\u51fa\u9519;\u8fd0\u884c\u65f6\u9519\u8bef;\u8fd0\u884c\u65f6\u95f4\u9519\u8bef;\u8fd0\u8f6c\u65f6\u51fa\u9519", "Concurrency Runtime": "\u5e76\u53d1\u8fd0\u884c\u65f6", "Common Runtime": "\u516c\u5171\u8fd0\u884c\u65f6;\u8bed\u8a00\u548c\u901a\u7528\u8fd0\u884c\u65f6;\u516c\u5171\u8fd0\u884c\u73af\u5883;\u8fd0\u884c\u5e93", "Runtime Database": "\u8fd0\u884c\u65f6\u6570\u636e\u5e93;\u8fd0\u884c\u6570\u636e\u5e93;\u5206\u5e03\u5f0f\u52a8\u6001\u6570\u636e\u5e93", "Captive Runtime": "\u8fd0\u884c\u65f6\u7ed1\u5b9a", "Runtime License": "\u8bb8\u53ef\u6388\u6743;\u8fd0\u884c\u8bb8\u53ef", "runtime host": "\u8fd0\u884c\u65f6\u4e3b\u673a;\u6267\u884c\u9636\u6bb5\u4e3b\u673a;\u5e93\u5bbf\u4e3b", "Reports Runtime": "\u4e0d\u6307\u5b9a\u62a5\u8868\u540d\u800c\u6253\u5f00;\u62a5\u8868\u8fd0\u884c\u5668"}, "eg2": []}, "Stitcher": {"ex": ["n. \u3014\u673a\u3015\u7f1d\u9488\uff1b\u62fc\u9022\u673a\uff1b\u9489\u7bb1\u673a\uff1b\u9f7f\u5f62\u538b\u6eda", "\u7f51\u7edc \u5e26\u6750\u7f1d\u5408\u673a\uff1b\u9489\u4e66\u673a\uff1b\u8ba2\u4e66\u673a"], "pron": {"peg": "\u82f1\u00a0['st\u026at\u0283\u0259] ", "pam": "\u7f8e\u00a0['st\u026at\u0283\u0259] "}, "eg2": []}, "WORKERS": {"ex": ["n. [\u52b3\u7ecf] \u5de5\u4eba\uff0c\u4eba\u5458\uff1b\u89d2\u8272\uff08worker\u590d\u6570\u5f62\u5f0f\uff09"], "pron": {"peg": "['w\u025dk\u025a]", "pam": "['w\u025dk\u025a]"}, "st": {}, "wp": {"Office workers": "\u4e0a\u73ed\u65cf;\u529e\u516c\u5ba4\u5de5\u4f5c\u4eba\u5458;\u529e\u516c\u5ba4\u804c\u5458;\u529e\u516c\u6905", "Construction workers": "\u5efa\u7b51\u5de5;\u5efa\u7b51\u5de5\u4eba;\u5efa\u7b51\u65bd\u5de5\u5458;\u65bd\u5de5\u5458", "Model Workers": "\u4fc4\u7f57\u65af\u52b3\u6a21;\u52b3\u6a21;\u52b3\u6a21\u98ce\u91c7", "retired workers": "\u9000\u4f11\u5de5\u4eba", "International Workers": "\u56fd\u9645\u793a\u5a01\u6e38\u884c\u65e5", "temporary workers": "\u4e34\u65f6\u5de5;\u6d41\u52a8\u5458\u5de5;\u6253\u4e34\u65f6\u5de5", "aid workers": "\u6551\u63f4\u4eba\u5458", "Warehouse workers": "\u4ed3\u7ba1\u5458", "Contract workers": "\u5408\u540c\u5de5;\u5951\u7ea6\u52b3\u52a8\u79fb\u6c11;\u5de5\u4f5c\u8005"}, "eg2": []}, "advert": {"pron": {"peg": "[\u00e6d\u02c8v\u025at]", "pam": "[\u00e6d\u02c8v\u025at]"}, "wp": {"Newspaper Advert": "\u6c99\u7279\u963f\u62c9\u4f2f", "aspekt advert": "\u533a\u57df\u6377\u514b\u4e70\u5bb6", "no advert": "\u666e\u901a\u8f6c\u5740\u670d\u52a1", "advert to": "\u6ce8\u610f;\u6ce8\u91cd;\u7559\u610f;\u8a00\u53ca", "ADVERT SERVICE": "\u5e7f\u544a\u670d\u52a1", "Advert Design": "\u62a5\u7ae0;\u62a5\u7ae0\u2571\u6742\u5fd7\u5e7f\u544a", "advert ising": "\u5e7f\u544a", "Bus Advert": "\u516c\u5171\u6c7d\u8f66\u5e7f\u544a\u56fe\u7247", "Advert price": "\u5e7f\u544a\u6536\u8d39"}, "ex": ["vi. \u6ce8\u610f\uff1b\u8c08\u5230", "n. \u5e7f\u544a", "n. (Advert)\u4eba\u540d\uff1b(\u6cd5)\u963f\u5fb7\u97e6\u5c14"], "eg2": [["For your viewing pleasure we have included a video clip of a Japanese  for this abomination.", "\u6211\u4eec\u526a\u8f91\u4e86\u4e00\u6bb5\u65e5\u672c\u5e7f\u544a\u7684\u89c6\u9891\u8ba9\u60a8\u5728\u89c6\u89c9\u4e0a\u611f\u53d7\u8fd9\u4efd\u6df1\u6076\u75db\u7edd\u3002"]], "st": {}}, "conspiracy": {"pron": {"peg": "[k\u0259n'sp\u026ar\u0259si]", "pam": "[k\u0259n'sp\u026ar\u0259si]"}, "wp": {"Shadow Conspiracy": "\u706b\u7ebf\u60ca\u7206\u70b9", "civil conspiracy": "\u6c11\u4e8b\u5171\u8c0b;\t\t\u6c11\u4e8b\u65b9\u9762\u7684\u5171\u8c0b", "conspiracy theories": "\u9634\u8c0b\u8bba;\u9634\u8c0b\u7406\u8bba;\u9634\u8c0b\u7684\u7406\u8bba", "Conspiracy Museum": "\u9634\u8c0b\u535a\u7269\u9986", "malicious conspiracy": "\u6076\u610f\u4e32\u901a", "Company Conspiracy": "\u516c\u53f8\u9634\u8c0b", "Echelon Conspiracy": "\u593a\u547d\u624b\u673a;\u7247;\u68af\u9635\u9634\u8c0b;\u6700\u8fd1\u89c2\u770b\u7684\u7535\u5f71", "Row Conspiracy": "\u767e\u5f97\u798f\u7279\u5a04\u9634\u8c0b", "conspiracy plotted": "\u7b56\u5212\u7684\u9634\u8c0b;\u9634\u8c0b\u7b56\u5212"}, "ex": ["n. \u9634\u8c0b\uff1b\u5171\u8c0b\uff1b\u9634\u8c0b\u96c6\u56e2"], "eg2": [["He was implicated in a .", "\u4ed6\u5377\u5165\u4e86\u4e00\u5b97\u9634\u8c0b\u3002"], ["We successfully thwarted the enemy's .", "\u6211\u4eec\u6210\u529f\u5730\u632b\u8d25\u4e86\u654c\u4eba\u7684\u9634\u8c0b\u3002"], ["If so, you may be the victim of a subliminal advertising !", "\u5982\u679c\u662f\u8fd9\u6837\uff0c\u4f60\u53ef\u80fd\u5c31\u6210\u4e86\u9608\u4e0b\u5e7f\u544a\u9634\u8c0b\u7684\u53d7\u5bb3\u8005\uff01"]], "st": {"transform": [["n.", "conspiracies"]], "similar": "plot"}}, "disbelief": {"ex": ["n. \u6000\u7591\uff0c\u4e0d\u4fe1"], "pron": {"peg": "[,d\u026asb\u026a'lif]", "pam": "[,d\u026asb\u026a'lif]"}, "st": {}, "wp": {"in disbelief": "\u6000\u7591\u5730;\u4e0d\u76f8\u4fe1;\u6000\u7591;\u96be\u4ee5\u7f6e\u4fe1\u5730", "T Disbelief": "\u9ed1\u8272\u91d1\u5c5e", "I disbelief": "\u6211\u4e0d\u76f8\u4fe1", "show disbelief": "\u8868\u793a\u4e0d\u76f8\u4fe1", "disbelief in": "\u4e0d\u76f8\u4fe1", "disbelief f": "\u6000\u7591", "Expressing Disbelief": "\u5bf9\u4ed6\u4eba\u89c2\u70b9\u8868\u793a\u6000\u7591\u65f6;\u5bf9\u522b\u4eba\u89c2\u5ff5\u8868\u793a\u7591\u5fc3\u65f6;\u4e0d\u8db3\u4e3a\u4fe1;\u7591\u60d1", "complete disbelief": "\u5b8c\u5168\u7684\u4e0d\u4fe1\u4efb", "To Disbelief": "\u5230\u96be\u4ee5\u7f6e\u4fe1"}, "eg2": [["Everyone in the room turned to look at me, either gasping or in .", "\u6bcf\u4e2a\u4eba\u7684\u76ee\u5149\u90fd\u805a\u7126\u5728\u6211\u8eab\u4e0a\uff0c\u6216\u5012\u5438\u4e86\u4e00\u53e3\u6c14\u6216\u5448\u73b0\u51fa\u4e0d\u4fe1\u4efb\u3002"], ["All across America, in living rooms and basements and sports bars, people broke into cries of wonderment and delight, heartbreak and .", "\u5728\u7f8e\u56fd\u7684\u5f88\u591a\u5ba2\u5385\u548c\u5730\u4e0b\u5ba4\uff0c\u4ee5\u53ca\u8fd0\u52a8\u9152\u5427\u91cc\uff0c\u4eba\u4eec\u56e0\u4e3a\u9ad8\u5174\u60ca\u8bb6\u6216\u8005\u5fc3\u788e\u6000\u7591\u800c\u7a81\u7136\u7206\u53d1\u51fa\u5c16\u53eb\u3002"], ["They're all scientific impossibilities, but since they take place on the silver screen, we suspend our<b> disbelief</b> and go along for the ride.", "\u90a3\u5168\u90fd\u662f\u79d1\u5b66\u4e0a\u4e0d\u53ef\u80fd\u5b8c\u6210\u7684\u4e8b\uff0c\u4f46\u662f\u81ea\u4ece\u5b83\u4eec\u5728\u8367\u5e55\u4e0a\u53d1\u751f\u540e\uff0c\u6211\u4eec\u5c31\u5c06\u6211\u4eec\u7684\u6000\u7591\u653e\u5728\u4e00\u8fb9\u7136\u540e\u4e00\u8d77\u53bb\u51d1\u90a3\u4efd\u70ed\u95f9\u3002"]]}, "outbreak": {"pron": {"peg": "['a\u028atbrek]", "pam": "['a\u028atbrek]"}, "wp": {"Sporadic outbreak": "\u70b9\u72b6\u7206\u53d1;\u6563\u53d1", "periodic outbreak": "\u5468\u671f\u6027\u5927\u53d1\u4f5c", "Virus Outbreak": "\u4f8b\u5982\u5728\u75c5\u6bd2\u7206\u53d1", "The outbreak": "\u7206\u53d1\u5427;\u7206\u53d1", "Emotional outbreak": "\u60c5\u7eea\u7206\u53d1", "polar outbreak": "\u5bd2\u6f6e;\u6781\u5730\u5bd2\u6f6e\u7206\u53d1;\u5bd2\u6f6e\u7206\u53d1", "outbreak n": "\u6218\u4e89", "Outbreak Survivalist": "\u52ab\u540e\u9980\u751f", "insect outbreak": "\u6606\u866b\u7684\u5927\u53d1\u751f"}, "ex": ["n. \uff08\u6218\u4e89\u7684\uff09\u7206\u53d1\uff1b\uff08\u75be\u75c5\u7684\uff09\u53d1\u4f5c", "vi. \u7206\u53d1"], "eg2": [["The cholera<b> outbreak</b> has been contained.", "\u970d\u4e71\u7684\u7206\u53d1\u5df2\u88ab\u904f\u5236\u4f4f\u3002"], ["Such events may forecast an<b> outbreak</b> of war.", "\u8fd9\u4e9b\u4e8b\u4ef6\u53ef\u80fd\u9884\u793a\u7740\u6218\u4e89\u7684\u7206\u53d1\u3002"], ["However, even in the early days of the , not everyone with swine flu will have visited their GP.", "\u7136\u800c\uff0c\u5373\u4f7f\u662f\u5728\u7206\u53d1\u65e9\u671f\uff0c\u4e5f\u505a\u4e0d\u5230\u6bcf\u4e00\u4e2a\u732a\u6d41\u611f\u75c5\u4eba\u90fd\u80fd\u62dc\u8bbf\u4ed6\u4eec\u7684\u5bb6\u5ead\u533b\u751f\u3002"]], "st": {"transform": [["vi.", "outbroke,outbroken,outbreaking"]]}}, "rehabilitation": {"ex": ["n. \u590d\u539f"], "pron": {"peg": "[\u02ccri\u02d0\u0259\u02ccb\u026al\u026a'te\u0283n]", "pam": "[\u02ccri\u02d0\u0259\u02ccb\u026al\u026a'te\u0283n]"}, "st": {}, "wp": {"Rehabilitation Medicine": "\u5eb7\u590d\u533b\u5b66;\u590d\u5065\u533b\u5b66;\u7597\u517b\u533b\u5b66;\u5eb7\u590d\u533b\u5b66\u7cfb", "Rehabilitation engineering": "\u5eb7\u590d\u5de5\u7a0b;\u5eb7\u590d\u5de5\u7a0b\u5b66;\u4fee\u590d\u5de5\u7a0b;\u590d\u5065\u5de5\u7a0b", "cardiac rehabilitation": "\u5fc3\u810f\u75c5\u5eb7\u590d;\u5fc3\u810f\u5eb7\u590d;\u5fc3\u810f\u5eb7\u590d\u5b66;\u5fc3\u810f\u5eb7\u590d\u533b\u5e08", "Comprehensive rehabilitation": "\u7efc\u5408\u5eb7\u590d;\u5168\u9762\u5eb7\u590d;\u7efc\u5408\u6027\u5eb7\u590d", "Rehabilitation Act": "\u5eb7\u590d\u6cd5\u6848;\u590d\u5065\u6cd5\u6848;\u5eb7\u590d\u6cd5;\u590d\u5065\u6cd5", "Rehabilitation Sciences": "\u590d\u5065\u5b66;\u5eb7\u590d\u79d1\u5b66;\u590d\u5065\u79d1\u5b66", "rehabilitation assessment": "\u5eb7\u590d\u8bc4\u4f30", "Rehabilitation Counsellor": "\u5eb7\u590d\u987e\u95ee;\u5eb7\u590d\u5de5\u4f5c\u987e\u95ee;\u5eb7\u590d\u53c2\u8d5e", "community rehabilitation": "\u793e\u533a\u5eb7\u590d;\u793e\u4f1a\u5eb7\u590d"}, "eg2": [["They can start the<b> rehabilitation</b> immediately.", "\u4ed6\u4eec\u9a6c\u4e0a\u80fd\u5f00\u59cb\u590d\u539f\u3002"], ["The doodle is the latest in the recent<b> rehabilitation</b> of Confucius.", "\u5728\u8fd1\u6765\u5b54\u5b50\u590d\u5174\u70ed\u4e2d\u8fd9\u4e2a\u6d82\u9e26\u662f\u6700\u65b0\u7684\u8868\u73b0\u3002"], ["The man, who appears to have some authority in the region, clearly wants money for reconstruction, and Christmas offers to fund the  of a mosque and a local restaurant in the bazaar.", "\u8fd9\u540d\u770b\u8d77\u6765\u4f3c\u4e4e\u5728\u5f53\u5730\u6709\u4e9b\u5f71\u54cd\u7684\u7537\u5b50\u5f88\u660e\u663e\u662f\u4e3a\u4e86\u91cd\u5efa\u8981\u6c42\u8d44\u91d1\uff0c\u800c\u514b\u91cc\u65af\u83ab\u65af\u8868\u793a\u613f\u610f\u4e3a\u590d\u539f\u6e05\u771f\u5bfa\u548c\u4e00\u5ea7\u96c6\u5e02\u91cc\u7684\u996d\u5e97\u7b79\u8d44\u3002"]]}, "retribution": {"ex": ["n. \u62a5\u5e94\uff1b\u60e9\u7f5a\uff1b\u62a5\u7b54\uff1b\u62a5\u507f"], "pron": {"peg": "[,r\u025btr\u026a'bju\u0283\u0259n]", "pam": "[,r\u025btr\u026a'bju\u0283\u0259n]"}, "st": {}, "wp": {"Retribution Retribution": "\u62a5\u507f", "Determined Retribution": "\u7b2c\u4e03\u5173", "Fated Retribution": "\u547d\u5b9a\u62a5\u5e94", "retribution karmique": "\u884c\u4e3a\u7684\u56e0\u679c\u62a5\u5e94", "Guaranteed Retribution": "\u5e94\u5141\u60e9\u6212", "proportional retribution": "\u6bd4\u4f8b\u6027\u62a5\u590d", "Retribution Theory": "\u62a5\u5e94\u8bba", "retribution stories": "\u62a5\u5e94\u8bf4\u8bdd", "retribution penalty": "\u62a5\u5e94\u5211"}, "eg2": []}, "sits": {"ex": ["v. \u5750\uff08sit\u7684\u7b2c\u4e09\u4eba\u79f0\u5355\u6570\u5f62\u5f0f\uff09", "n. \u5750\uff08sit\u7684\u590d\u6570\uff09"], "pron": {}, "st": {}, "wp": {"sits around": "\u5750\u5728\u5468\u56f4;\u5750\u5728\u90a3\u91cc\u770b;\u5750\u5728", "Sits gentleman": "\u5750\u7684\u58eb", "Sits straight": "\u5750\u7aef\u6b63", "binding sits": "\u7ed3\u5408\u4f4d", "Sits Then": "\u5750\u4fbf", "Wall sits": "\u9760\u5899\u5750;\u76f4\u89d2\u5750\u5899", "active sits": "\u6d3b\u6027\u4f4d", "Buddy Sits": "\u5df4\u8fea\u5c31\u5750\u4e0b", "SITS bits": "\u5206\u949f"}, "eg2": []}, "suspicion": {"pron": {"peg": "[s\u0259'sp\u026a\u0283\u0259n]", "pam": "[s\u0259'sp\u026a\u0283\u0259n]"}, "wp": {"Beyond Suspicion": "\u558b\u8840\u8ffd\u7f09\u4ee4;\u558b\u8840\u8ffd\u8f91\u4ee4;\u5373\u8d85\u51fa\u731c\u6d4b", "The suspicion": "\u78be\u6838\u91d1\u5c5e;\u7b2c\u4e8c\u5173\u7591\u8651", "spawn suspicion": "\u4ea7\u751f\u7591\u60d1", "Suspicion Business": "\u987a\u4fbf\u5f0f\u8425\u4e1a\u91cf", "of suspicion": "\u8bba\u731c\u7591", "genuine suspicion": "\u771f\u6b63\u5acc\u7591", "Suspicion ofProcris": "\u80e1\u4e71\u731c\u7591", "suspicion level": "\u6000\u7591\u7ea7\u522b", "on suspicion": "\u56e0\u5acc\u7591;\u6839\u636e\u731c\u60f3"}, "ex": ["n. \u6000\u7591\uff1b\u5acc\u7591\uff1b\u7591\u5fc3\uff1b\u4e00\u70b9\u513f", "vt. \u6000\u7591"], "eg2": [[" chased itself across his face.", "\u4ed6\u7684\u8138\u4e0a\u9732\u51fa\u6000\u7591\u7684\u795e\u8272\u3002"], ["His conduct roused the  of the police.", "\u4ed6\u7684\u4e3e\u52a8\u5f15\u8d77\u4e86\u8b66\u5bdf\u7684\u6000\u7591\u3002"], ["The police booked him for<b> suspicion</b> of robbery.", "\u8b66\u65b9\u628a\u4ed6\u4f5c\u4e3a\u76d7\u7a83\u5acc\u7591\u72af\u767b\u8bb0\u5165\u518c\u3002"]], "st": {}}, "tackle": {"ex": ["v. \u5904\u7406\uff1b\u963b\u622a\uff1b\u4e0e\u67d0\u4eba\u4ea4\u6d89\uff1b\u5411\u67d0\u4eba\u63d0\u8d77\uff08\u95ee\u9898\u6216\u56f0\u96be\u60c5\u51b5\uff09", "n. \u7528\u5177\uff1b\u963b\u622a\uff1b\u963b\u622a\u94f2\u7403\uff1b\u963b\u622a\u961f\u5458", "\u7f51\u7edc \u89e3\u51b3\uff1b\u6ed1\u8f66\uff1b\u5bf9\u4ed8"], "pron": {"peg": "\u82f1\u00a0['t\u00e6k(\u0259)l] ", "pam": "\u7f8e\u00a0['t\u00e6k(\u0259)l] "}, "eg2": [["The government is determined to tackle inflation.", "\u653f\u5e9c\u51b3\u5fc3\u89e3\u51b3\u901a\u8d27\u81a8\u80c0\u95ee\u9898\u3002"], ["I tackled him about the money he owed me.", "\u6211\u5c31\u4ed6\u6b20\u6211\u94b1\u7684\u4e8b\u4e0e\u4ed6\u8fdb\u884c\u4e86\u4ea4\u6d89\u3002"], ["He was tackled just outside the penalty area.", "\u4ed6\u5c31\u5728\u7981\u533a\u5916\u8ba9\u5bf9\u65b9\u628a\u7403\u62a2\u65ad\u3002"], ["He tackled a masked intruder at his home.", "\u4ed6\u5728\u5bb6\u91cc\u6293\u4f4f\u4e86\u4e00\u4e2a\u79c1\u81ea\u95ef\u5165\u7684\u8499\u9762\u4eba\u3002"]]}, "violent": {"pron": {"peg": "['va\u026a\u0259l\u0259nt]", "pam": "['va\u026a\u0259l\u0259nt]"}, "wp": {"violent folding": "\u5267\u70c8\u8936\u76b1\u4f5c\u7528", "violent incidents": "\u66b4\u529b\u4e8b\u4ef6", "Violent Beauty": "\u6b8b\u66b4\u4e4b\u7f8e;\u66b4\u4e4b\u7f8e", "violent acceleration": "\u6025\u5267\u52a0\u901f", "Violent Playground": "\u66b4\u529b\u6e38\u4e50\u573a;\u66b4\u5f92\u5730\u5e26", "violent ken": "\u6d17\u8111\u80af", "violent possession": "\u66b4\u529b\u5360\u6709", "Violent Lolita": "\u66b4\u529b\u4e0e\u55dc\u6740", "violent flood": "\u66b4\u6d2a"}, "ex": ["adj. \u66b4\u529b\u7684\uff1b\u731b\u70c8\u7684"], "eg2": [["The black cloud presignified a<b> violent</b> storm.", "\u4e4c\u4e91\u9884\u793a\u7740\u4e00\u573a\u731b\u70c8\u7684\u66b4\u98ce\u96e8\u3002"], ["The speaker lashed the young people into<b> violent</b> action.", "\u90a3\u4e2a\u6f14\u8bb2\u8005\u717d\u52a8\u9752\u5e74\u4eba\u641e\u66b4\u529b\u884c\u52a8\u3002"], ["The enemy troops began to reel in defeat under our<b> violent</b> attack.", "\u654c\u519b\u5728\u6211\u65b9\u7684\u731b\u70c8\u653b\u51fb\u4e0b\u5f00\u59cb\u6e83\u9000\u3002"]], "st": {}}}, "Title": "\u201cHalf the people in the Ebola zone don't believe that Ebola is real\u201d\u2014Congo\u2019s year-long outbreak\n", "paperStatistics": {"suggestedfocus": "17.7 Minutes", "wordsset": 73, "keywords": "Congo,Ebola,battle,economist,history,https,outbreak,www", "toughwords": 67, "allwords": 84, "title": "\u201cHalf the people in the Ebola zone don't believe that Ebola is real\u201d\u2014Congo\u2019s year-long outbreak\n", "desc": "https://www.economist.com/sites/default/files/20190803_blm510.jpg\n", "img": "https://www.economist.com/sites/default/files/20190803_blm510.jpg\n", "date": "2019-08-02 20:09:24", "link": "2019_8_2_1.json"}}