{"words": {"amend": {"pron": {"peg": "[\u0259'm\u025bnd]", "pam": "[\u0259'm\u025bnd]"}, "wp": {"Wi amend": "\u74e6\u5c14\u7279", "Particia Amend": "\u963f\u66fc\u5fb7", "Patricia Amend": "\u963f\u66fc\u8fbe;\u963f\u66fc\u5fb7;\u6d3e\u7fe0\u897f\u4e9a\u00b7\u963f\u66fc\u5fb7", "amend theory": "\u4fee\u6b63\u7406\u8bba", "AMND Amend": "\u4fee\u6539", "batch amend": "\u6279\u6b21\u66f4\u65b0", "amend contract": "\u597d\u7403\u5458\u5c31\u8981\u7eed\u7b7e", "curve amend": "\u66f2\u7ebf\u4fee\u6b63", "amend SPIHT": "\u6539\u8fdb\u591a\u7ea7\u6811\u96c6\u5408\u5206\u88c2\u7b97\u6cd5"}, "ex": ["vt. \u4fee\u6539\uff1b\u6539\u5584\uff0c\u6539\u8fdb", "vi. \u6539\u6b63\uff0c\u6539\u5584\uff1b\u6539\u8fc7\u81ea\u65b0", "n. (Amend)\u4eba\u540d\uff1b(\u5fb7\u3001\u82f1)\u963f\u95e8\u5fb7"], "eg2": [["Set up a sound administrative system to serve and guide private investment and<b> amend</b> unfavorable laws and regulations.", "\u5efa\u7acb\u4e00\u4e2a\u5065\u5eb7\u7684\u7ba1\u7406\u7cfb\u7edf\u6765\u6307\u5bfc\u548c\u670d\u52a1\u4e8e\u79c1\u6709\u6295\u8d44\u5e76\u4fee\u6539\u4e0d\u5229\u7684\u6cd5\u5f8b\u89c4\u5b9a\u3002"], ["Once you start monitoring what people are saying about you or your product, you may find inaccuracies or incomplete statements. There are a few ways you can<b> amend</b> and respond to them.", "\u4e00\u65e6\u4f60\u5f00\u59cb\u5728\u7f51\u4e0a\u76d1\u63a7\u4eba\u4eec\u90fd\u5bf9\u4f60\u6216\u8005\u4f60\u7684\u4ea7\u54c1\u8bf4\u4e86\u4e9b\u4ec0\u4e48\u7684\u65f6\u5019\uff0c\u4f60\u4f1a\u53d1\u73b0\u6709\u4e00\u4e9b\u4e0d\u7cbe\u786e\u6216\u8005\u4e0d\u5168\u9762\u7684\u9648\u8ff0\u3001\u8fd9\u91cc\u6709\u4e00\u4e9b\u4f60\u53ef\u4ee5\u91c7\u53d6\u7684\u65b9\u6cd5\u4ee5\u6539\u5584\u548c\u56de\u5e94\u4ed6\u4eec\u3002"]], "st": {}}, "tribunal": {"pron": {"peg": "\u82f1\u00a0[tra\u026a'bju\u02d0n(\u0259)l] ", "pam": "\u7f8e\u00a0[tr\u026a'bjun(\u0259)l] "}, "ex": ["n. \u7279\u522b\u6cd5\u5ead\uff1b\u88c1\u5224\u6240", "\u7f51\u7edc \u5ba1\u88c1\u5904\uff1b\u6cd5\u5b98\u5e2d\uff1b\u6cd5\u9662"], "eg2": [["an international war crimes tribunal", "\u56fd\u9645\u6218\u4e89\u7f6a\u6cd5\u5ead"], ["a military tribunal", "\u519b\u4e8b\u6cd5\u5ead"]]}, "parliament": {"pron": {"peg": "\u82f1\u00a0['p\u0251\u02d0(r)l\u0259m\u0259nt] ", "pam": "\u7f8e\u00a0['p\u0251rl\u0259m\u0259nt] "}, "ex": ["n. \u8bae\u4f1a\uff1b\u56fd\u4f1a\uff1b\u82f1\u56fd\u8bae\u4f1a\uff08\u5305\u62ec\u4e0b\u8bae\u9662\u548c\u4e0a\u8bae\u9662\uff09\uff1b\u4e00\u5c4a\u8bae\u4f1a\u7684\u4f1a\u671f", "\u7f51\u7edc \u767e\u4e50\u95e8\uff1b\u56fd\u4f1a\u5927\u53a6\uff1b\u8bae\u4f1a\u5927\u53a6"], "eg2": [["The German parliament is called the \u2018Bundestag\u2019.", "\u5fb7\u56fd\u7684\u8bae\u4f1a\u79f0\u4e3a Bundestag\u3002"], ["a Member of Parliament", "\u8bae\u4f1a\u8bae\u5458"], ["The issue was debated in Parliament .", "\u8bae\u4f1a\u5c31\u8fd9\u4e2a\u95ee\u9898\u8fdb\u884c\u4e86\u8fa9\u8bba\u3002"], ["an Act of Parliament", "\u8bae\u4f1a\u6cd5\u6848"], ["to win a seat in Parliament", "\u8d62\u5f97\u8bae\u4f1a\u4e2d\u7684\u4e00\u4e2a\u5e2d\u4f4d"], ["to be elected to Parliament", "\u5f53\u9009\u4e3a\u8bae\u4f1a\u8bae\u5458"], ["We are now into the second half of the parliament.", "\u6211\u4eec\u73b0\u5df2\u8fdb\u5165\u4e86\u672c\u5c4a\u8bae\u4f1a\u7684\u540e\u534a\u4efb\u671f\u3002"], ["to dissolve Parliament(= formally end its activities) and call an election", "\u89e3\u6563\u8bae\u4f1a\u5e76\u4e3e\u884c\u5927\u9009"]]}, "irregularly": {"pron": {"peg": "[\u026a'r\u025bgj\u0259l\u025ali]", "pam": "[\u026a'r\u025bgj\u0259l\u025ali]"}, "wp": {}, "ex": ["adv. \u4e0d\u89c4\u5219\u5730\uff1b\u4e0d\u6574\u9f50\u5730"], "eg2": [["Are there a lot of rectangular elements or many<b> irregularly</b> shaped elements?", "\u662f\u5426\u6709\u5927\u91cf\u7684\u77e9\u5f62\u5143\u7d20\u6216\u662f\u4f17\u591a\u4e0d\u89c4\u5219\u5f62\u6001\u7684\u5143\u7d20\uff1f"], ["Good golfers do better if they give themselves little time to prepare for their shots--and even better if they are distracted by researchers asking them to count<b> irregularly</b> spaced sounds.", "\u4f18\u79c0\u7684\u9ad8\u5c14\u592b\u7403\u624b\u5728\u51fb\u7403\u524d\u51c6\u5907\u7684\u65f6\u95f4\u8d8a\u5c11\u6210\u7ee9\u8d8a\u597d\u2014\u5373\u4f7f\u88ab\u7814\u7a76\u4eba\u5458\u9a9a\u6270\uff0c\u8ba9\u4ed6\u4eec\u6570\u4e0d\u89c4\u5219\u95f4\u9694\u7684\u58f0\u54cd\uff0c\u6700\u540e\u51fb\u7403\u6210\u7ee9\u4f9d\u7136\u4e0d\u4fd7\u3002"], ["Multiple contiguous or<b> irregularly</b> inserted grouping separators prior to a decimal separator are ignored.", "\u5728\u5c0f\u6570\u5206\u9694\u7b26\u524d\u63d2\u5165\u7684\u591a\u4e2a\u6328\u7740\u7684\u6216\u4e0d\u89c4\u5219\u7684\u5206\u7ec4\u5206\u9694\u7b26\u88ab\u5ffd\u7565\u4e86\u3002"]], "st": {"similar": "abnormal,anomalous,unnatural"}}, "imminent": {"pron": {"peg": "['\u026am\u026an\u0259nt]", "pam": "['\u026am\u026an\u0259nt]"}, "wp": {"imminent anomaly": "\u77ed\u4e34\u5f02\u5e38", "Seems Imminent": "\u8fd9\u4f3c\u4e4e\u8feb\u5728\u7709\u776b", "Appeared Imminent": "\u663e\u5f97\u8feb\u5728\u7709\u776b", "Imminent attack": "\u654c\u4eba\u7684\u8fdb\u653b\u4e5f\u8d8a\u6765\u8d8a\u8fd1", "clearly imminent": "\u53ef\u80fd\u6027;\u8feb\u5728\u7709\u776b", "imminent toward": "\u903c\u8fd1\u7684", "Imminent Starvation": "\u8868\u6f14\u8005", "imminent failure": "\u5373\u65f6\u635f\u6bc1;\u5373\u65f6\u6bc1\u574f", "imminent danger": "\u8feb\u5207\u5371\u9669;\u8feb\u5728\u7709\u776b\u7684\u5371\u9669;\u6025\u8feb\u7684\u5371\u9669;\u7d27\u6025\u5371\u9669"}, "ex": ["adj. \u5373\u5c06\u6765\u4e34\u7684\uff1b\u8feb\u8fd1\u7684"], "eg2": [["But still we have the character like Prince Hamlet, lacking iller instinct destroyed, by the<b> imminent</b> achievement of desires.", "\u4f46\u6211\u4eec\u4ecd\u6709\u50cf\u54c8\u59c6\u96f7\u7279\u738b\u5b50\u90a3\u6837\u7684\u4eba\u7269\uff0c\u56e0\u7f3a\u4e4f\u201c\u6740\u624b\u7684\u672c\u80fd\u201d\uff0c\u88ab\u6b32\u671b\u5373\u5c06\u6765\u4e34\u7684\u5b9e\u73b0\u800c\u6bc1\u706d\u3002"], ["If change is  in your household, then try and follow these tips and lets see if we can make the change easier and better for all.", "\u5982\u679c\u4f60\u5bb6\u91cc\u8fd9\u4e2a\u8f6c\u53d8\u5373\u5c06\u6765\u4e34\uff0c\u8981\u8bd5\u7740\u9075\u5faa\u8fd9\u4e9b\u5c0f\u6280\u5de7\uff0c\u7136\u540e\u770b\u770b\u6211\u4eec\u662f\u5426\u80fd\u4f7f\u8fd9\u4e2a\u8f6c\u53d8\u53d8\u5f97\u66f4\u5bb9\u6613\u66f4\u597d\u3002"], ["As the impact of the<b> imminent</b> Great Disruption hits us, he says, \u201cour response will be proportionally dramatic, mobilizing as we do in war.", "\u5f53\u5373\u5c06\u6765\u4e34\u7684\u5927\u5d29\u89e3\u7684\u51b2\u51fb\u6b83\u53ca\u6211\u4eec\u65f6\uff0c\u4ed6\u8bf4\uff1a\u201c\u6211\u4eec\u7684\u53cd\u5e94\u4e5f\u5c06\u76f8\u5e94\u5730\u5de8\u5927\uff0c\u5982\u540c\u6211\u4eec\u5728\u6218\u4e89\u4e2d\u505a\u7684\u90a3\u6837\u52a8\u5458\u8d77\u6765\u3002"]], "st": {}}, "egregiously": {"pron": {"peg": "[\u026a'gr\u026ad\u0292\u0259sli]", "pam": "[\u026a'gr\u026ad\u0292\u0259sli]"}, "wp": {}, "ex": ["adv. \u60ca\u4eba\u5730\uff1b\u5f02\u4e4e\u5bfb\u5e38\u5730\uff1b\u8fc7\u4efd\u5730\uff1b\u5353\u8d8a\u5730"], "eg2": [["Most , these shady real estate deals victimized American Air Force pilots who were stationed in Japan but wanted home sites in the United States.", "\u6700\u4e3a\u8fc7\u5206\u7684\u662f\uff0c\u8fd9\u4e9b\u9634\u6697\u7684\u623f\u5730\u4ea7\u4ea4\u6613\u5371\u5bb3\u4e86\u9a7b\u519b\u5728\u65e5\u672c\u4f46\u53c8\u60f3\u8981\u5728\u56fd\u5185\u8d2d\u7f6e\u623f\u4ea7\u7684\u7f8e\u56fd\u7a7a\u519b\u98de\u884c\u5458\u3002"]], "st": {}}, "prosecutor": {"pron": {"peg": "\u82f1\u00a0['pr\u0252s\u026akju\u02d0t\u0259(r)] ", "pam": "\u7f8e\u00a0['pr\u0251s\u026a.kjut\u0259r] "}, "ex": ["n. \u68c0\u5bdf\u5b98\uff1b\u516c\u8bc9\u4eba\uff1b\u539f\u544a\u5f8b\u5e08\uff1b\u63a7\u65b9\u5f8b\u5e08", "\u7f51\u7edc \u8d77\u8bc9\u4eba\uff1b\u68c0\u4e3e\u4eba\uff1b\u68c0\u67e5\u5b98"], "eg2": [["the public/state prosecutor", "\u516c\u8bc9\u4eba\uff1b\u5dde\u68c0\u5bdf\u5b98"]]}, "transgression": {"pron": {"peg": "[tr\u00e6nz'\u0261r\u025b\u0283\u0259n]", "pam": "[tr\u00e6nz'\u0261r\u025b\u0283\u0259n]"}, "wp": {"continental transgression": "\u9646\u76f8\u6c89\u79ef\u6269\u5c55;\u9646\u4fb5", "Atel transgression": "\u963f\u8482\u5c14\u6d77\u8fdb", "gene transgression": "\u57fa\u56e0\u6e17\u5165", "transgression breeding": "\u8d85\u4eb2\u80b2\u79cd;\u8d8a\u4eb2\u80b2\u79cd", "erosional transgression": "\u4fb5\u8680\u6d77\u8fdb", "Cenomanian transgression": "\u68ee\u8bfa\u66fc\u6d77\u4fb5", "cretaceous transgression": "\u767d\u57a9\u7eaa\u6d77\u8fdb", "marine transgression": "\u6d77\u4fb5;\t\t\u6d77\u8fdb;\u6d77\u8fd1", "Subjective Transgression": "\u4e3b\u4f53\u903e\u8d8a"}, "ex": ["n. [\u5730\u8d28] \u6d77\u4fb5\uff1b\u72af\u7f6a\uff1b\u8fdd\u53cd\uff1b\u9038\u51fa"], "eg2": [["In scientific terms the findings showed that \"the embodiment of moral purity is specific to the motor modality involved in the moral .", "\u7528\u79d1\u5b66\u7684\u672f\u8bed\u6765\u8bb2\uff0c\u8fd9\u4e2a\u7814\u7a76\u8868\u660e\u201c\u4fdd\u6301\u9053\u5fb7\u7eaf\u6d01\u7684\u5177\u4f53\u8868\u73b0\u662f\u7279\u5b9a\u4e8e\u5404\u79cd\u8fdd\u53cd\u9053\u5fb7\u7684\u884c\u4e3a\u65b9\u5f0f\u201d\u3002"], ["Nevertheless death reigned from Adam to Moses, even over them that had not sinned after the similitude of Adam\\'s , who is the figure of him that was to come.", "\u7136\u800c\u4ece\u4e9a\u5f53\u5230\u6469\u897f\uff0c\u6b7b\u5c31\u4f5c\u4e86\u738b\uff0c\u8fde\u90a3\u4e9b\u4e0d\u4e0e\u4e9a\u5f53\u72af\u4e00\u6837\u7f6a\u8fc7\u7684\uff0c\u4e5f\u5728\u4ed6\u7684\u6743\u4e0b\u3002 \u4e9a\u5f53\u4e43\u662f\u90a3\u4ee5\u540e\u8981\u6765\u4e4b\u4eba\u7684\u9884\u50cf\u3002"], ["Capitalism, we should have remembered, involves at once prudent regulation and the imprudent<b> transgression</b> of old rules, the sharing of risks and the audacity to risk more successfully than others.", "\u6211\u4eec\u5e94\u8be5\u8bb0\u4f4f\uff0c\u8d44\u672c\u4e3b\u4e49\u540c\u65f6\u5177\u5907\u5ba1\u614e\u7684\u89c4\u5219\u4ee5\u53ca\u5bf9\u65e7\u89c4\u5219\u9c81\u83bd\u7684\u8fdd\u53cd\uff0c\u98ce\u9669\u7684\u5206\u62c5\u4ee5\u53ca\u5bf9\u98ce\u9669\u7684\u6beb\u65e0\u987e\u5fcc\uff0c\u90fd\u8fdc\u751a\u4e8e\u4ed6\u8005\u3002"]], "st": {}}, "prosecute": {"pron": {"peg": "['pr\u0251s\u026a'kj\u028at]", "pam": "['pr\u0251s\u026a'kj\u028at]"}, "wp": {"prosecute sb": "\u8d77\u8bc9\u67d0\u4eba", "prosecute e": "\u544a\u53d1", "public prosecute": "\u516c\u8bc9", "prosecute power": "\u68c0\u5bdf\u6743", "Prosecute Violations": "\u4f9d\u6cd5\u67e5\u5904\u8fdd\u6cd5\u884c\u4e3a", "maliciously prosecute": "\u8bec\u544a\u9677\u5bb3", "civil prosecute": "\u6c11\u4e8b\u516c\u8bc9", "prosecute system": "\u8d77\u8bc9\u5236\u5ea6", "Prosecute Them": "\u8d77\u8bc9\u4ed6\u4eec"}, "ex": ["vt. \u68c0\u4e3e\uff1b\u8d2f\u5f7b\uff1b\u4ece\u4e8b\uff1b\u4f9d\u6cd5\u8fdb\u884c", "vi. \u8d77\u8bc9\uff1b\u544a\u53d1\uff1b\u4f5c\u68c0\u5bdf\u5b98"], "eg2": [["The state could<b> prosecute</b> a person, but could not require that he or she assist in that process.", "\u653f\u5e9c\u53ef\u4ee5\u8d77\u8bc9\u4e00\u4e2a\u4eba\uff0c\u4f46\u4e0d\u53ef\u4ee5\u8981\u6c42\u8fd9\u4e2a\u4eba\u4e3a\u8fd9\u4e2a\u8fc7\u7a0b\u63d0\u4f9b\u534f\u52a9\u3002"], ["Those in positions of responsibility, who should have known about the crime (or its planning) and who failed to prevent it or<b> prosecute</b> those responsible, should be held criminally responsible.", "\u90a3\u4e9b\u62c5\u4efb\u8d23\u4efb\u804c\u52a1\u7684\u4eba, \u4ed6\u4eec\u5e94\u8be5\u5df2\u77e5\u9053\u7f6a\u884c\uff08\u6216\u8ba1\u5212\uff09, \u548c\u90a3\u4e9b\u6ca1\u6709\u963b\u6b62\u6216\u8d77\u8bc9\u8d23\u4efb\u4eba\u7684\u4eba, \u5e94\u88ab\u4f9d\u6cd5\u8ffd\u7a76\u5211\u4e8b\u8d23\u4efb\u3002"], ["He says possession of smallpox by those not authorized to have it should be made a crime against humanity and that international authorities should<b> prosecute</b> any country found with it.", "\u4ed6\u8bf4\u90a3\u4e9b\u6ca1\u6709\u88ab\u6279\u51c6\u7684\u53ef\u4ee5\u5b58\u7559\u5929\u82b1\u7684\u56fd\u5bb6\u79c1\u81ea\u5b58\u7559\u5929\u82b1\u5e94\u8be5\u88ab\u5224\u5904\u53cd\u4eba\u7c7b\u7f6a\uff0c\u5e76\u4e14\u56fd\u9645\u6cd5\u5ead\u5e94\u8be5\u8d77\u8bc9\u4efb\u4f55\u88ab\u53d1\u73b0\u5b58\u7559\u5929\u82b1\u7684\u56fd\u5bb6\u3002"]], "st": {"transform": [["vt.", "prosecuted,prosecuting"]]}}, "Smolensk": {"ex": ["\u7f51\u7edc \u65af\u6469\u68f1\u65af\u514b\uff1b\u4fc4\u7f57\u65af\u65af\u6469\u68f1\u65af\u514b\uff1b\u6797\u65af\u514b"], "pron": {"peg": "\u82f1\u00a0", "pam": "\u7f8e\u00a0"}, "eg2": []}, "fascist": {"pron": {"peg": "\u82f1\u00a0['f\u00e6\u0283\u026ast] ", "pam": "\u7f8e\u00a0['f\u00e6\u0283\u026ast] "}, "ex": ["n. \u6cd5\u897f\u65af\u4e3b\u4e49\u8005\uff1b\u6781\u53f3\u5206\u5b50", "adj. \u6cd5\u897f\u65af\u4e3b\u4e49\u7684", "\u7f51\u7edc \u6cd5\u897f\u65af\u5206\u5b50\uff1b\u6cd5\u897f\u65af\u4efd\u5b50\uff1b\u6cd5\u897f\u65af\u515a\u5458"], "eg2": []}, "sack": {"pron": {"peg": "\u82f1\u00a0[s\u00e6k] ", "pam": "\u7f8e\u00a0[s\u00e6k] "}, "ex": ["n. \u89e3\u96c7\uff1b\u7092\u9c7f\u9c7c\uff1b\u5f00\u9664\uff1b\u5e8a", "v. \u89e3\u96c7\uff1b\u7092\u9c7f\u9c7c\uff1b\uff08\u5c24\u6307\u65e7\u65f6\u519b\u961f\u7b49\uff09\u7834\u574f\uff1b\u64d2\u6740\uff08\u56db\u5206\u536b\uff09", "\u7f51\u7edc \u9ebb\u888b\uff1b\u888b\u5b50\uff1b\u5305"], "eg2": [["They got through a sack of potatoes.", "\u4ed6\u4eec\u628a\u4e00\u9ebb\u888b\u571f\u8c46\u5403\u5b8c\u4e86\u3002"], ["two sacks of groceries", "\u4e24\u888b\u98df\u54c1\u6742\u8d27"], ["He got the sack for swearing.", "\u4ed6\u56e0\u8bf4\u810f\u8bdd\u800c\u88ab\u5f00\u9664\u3002"], ["Her work was so poor that she was given the sack .", "\u5979\u5de5\u4f5c\u5e72\u5f97\u5f88\u5dee\uff0c\u88ab\u7092\u4e86\u9c7f\u9c7c\u3002"], ["Four hundred workers face the sack.", "\u56db\u767e\u540d\u5de5\u4eba\u9762\u4e34\u89e3\u96c7\u7684\u5371\u9669\u3002"], ["He caught them in the sack together.", "\u4ed6\u649e\u89c1\u4ed6\u4eec\u4fe9\u4e00\u8d77\u7761\u5728\u5e8a\u4e0a\u3002"], ["the sack of Rome", "\u5bf9\u7f57\u9a6c\u57ce\u7684\u6d17\u52ab"], ["She was sacked for refusing to work on Sundays.", "\u5979\u56e0\u62d2\u7edd\u5728\u661f\u671f\u5929\u4e0a\u73ed\u88ab\u89e3\u96c7\u4e86\u3002"], ["Rome was sacked by the Goths in 410.", "\u7f57\u9a6c\u5728 410 \u5e74\u906d\u5230\u54e5\u7279\u4eba\u7684\u6d17\u52ab\u3002"]]}, "diplomatic": {"pron": {"peg": "[,d\u026apl\u0259'm\u00e6t\u026ak]", "pam": "[,d\u026apl\u0259'm\u00e6t\u026ak]"}, "wp": {"diplomatic status": "\u5916\u4ea4\u8eab\u4efd", "Diplomatic Studies": "\u5916\u4ea4\u7814\u7a76;\u5916\u4ea4\u5b66", "Diplomatic Visa": "\u5916\u4ea4\u7b7e\u8bc1", "diplomatic immunity": "\u5916\u4ea4\u8c41\u514d\u6743;\u5916\u4ea4\u8c41\u514d;\u5916\u4ea4\u5bbd\u514d\u6743;\u8d8a\u754c\u683c\u6740", "Diplomatic Hotel": "\u5916\u4ea4\u9152\u5e97", "diplomatic protocol": "\u5916\u4ea4\u793c\u8282;\u5916\u4ea4\u793c\u4eea", "diplomatic rank": "\u5916\u4ea4\u5b98\u8854;\u793e\u4ea4\u5b98\u8854;\u4ea4\u9645\u5b98\u8854;\u916c\u9162\u5b98\u8854", "diplomatic service": "\u5916\u4ea4\u90e8\u95e8;\u540e\u5728\u5916\u4ea4\u90e8\u95e8;\u5916\u4ea4\u4e8b\u52a1;\u97e9\u56fd\u5916\u4ea4\u90e8\u95e8", "Diplomatic Corps": "\u5916\u4ea4\u4f7f\u8282\u56e2;\u5916\u4ea4\u4f7f\u56e2;\u5916\u4ea4\u56e2;\u5916\u4ea4\u5b98"}, "ex": ["adj. \u5916\u4ea4\u7684\uff1b\u5916\u4ea4\u4e0a\u7684\uff1b\u8001\u7ec3\u7684"], "eg2": [["This would be against<b> diplomatic</b> etiquette.", "\u8fd9\u5c06\u5728\u5916\u4ea4\u4e0a\u72af\u5931\u793c\u7684\u9519\u8bef\u3002"], ["He has long credentials of<b> diplomatic</b> service.", "\u4ed6\u7684\u5916\u4ea4\u5de5\u4f5c\u8d44\u5386\u5f88\u6df1\u3002"], ["He was more than my match in<b> diplomatic</b> shrewdness.", "\u8bba\u5916\u4ea4\u624b\u8155\u4e4b\u7cbe\u660e\uff0c \u6211\u8fdc\u4e0d\u654c\u4ed6\u3002"]], "st": {"similar": "suave"}}, "corp": {"ex": ["abbr. \u516c\u53f8\uff08\u7b49\u4e8ecorporation \uff09", "n. (Corp)\u4eba\u540d\uff1b(\u745e\u5178)\u79d1\u5c14\u666e"], "pron": {"peg": "['k\u0254rp]", "pam": "['k\u0254rp]"}, "st": {}, "wp": {"SONY CORP": "\u7d22\u5c3c\u516c\u53f8;\u65b0\u529b\u516c\u53f8;\u65e5\u672c\u7d22\u5c3c\u516c\u53f8", "Microsoft Corp": "\u5fae\u8f6f\u516c\u53f8;\u4e0e\u5fae\u8f6f;\u4e8e\u5fae\u8f6f;\u5bf9\u5fae\u8f6f", "Greed Corp": "\u8d2a\u5a6a\u516c\u53f8;\u8d2a\u5fc3\u516c\u53f8;\u786c\u76d8\u7248;\u8d2a\u5a6a\u5175\u5de5\u5382", "toshiba corp": "\u4e1c\u829d\u516c\u53f8;\u4e1c\u829d\u96c6\u56e2;\u65e5\u672c\u4e1c\u829d\u516c\u53f8", "Nokia Corp": "\u8bfa\u57fa\u4e9a\u516c\u53f8;\u8bfa\u57fa\u4e9a;\u82ac\u5170\u8bfa\u57fa\u4e9a;\u4e8e\u8bfa\u57fa\u4e9a", "Marubeni Corp": "\u4e38\u7ea2\u682a\u5f0f\u4f1a\u793e;\u4e38\u7ea2\u516c\u53f8;\u65e5\u672c\u4e38\u7ea2\u682a\u5f0f\u4f1a\u793e;\u8d38\u6613\u516c\u53f8\u4e38\u7ea2", "SOFTBANK Corp": "\u8f6f\u94f6\u96c6\u56e2;\u8f6f\u94f6\u516c\u53f8;\u65e5\u672c\u8f6f\u94f6;\u8f6f\u4f53\u94f6\u884c", "Wachovia Corp": "\u7f8e\u8054\u94f6\u884c;\u7ef4\u4e9a\u94f6\u884c;\u74e6\u4e54\u7ef4\u4e9a\u516c\u53f8;\u4ee5\u53ca\u8c0b\u6c42\u4e0e\u74e6\u4e54\u7ef4\u4e9a", "Shin Corp": "\u81e3\u90a3\u8d8a\u96c6\u56e2;\u65b0\u96c6\u56e2;\u4fe1\u96c6\u56e2;\u81e3\u90a3\u8d8a"}, "eg2": []}, "rehire": {"pron": {"peg": "[ri:'hai\u0259]", "pam": "[ri:'hai\u0259]"}, "wp": {}, "ex": ["vt. \u91cd\u65b0\u96c7\u7528\uff1b\u4e8c\u6b21\u96c7\u7528", "n. \u518d\u96c7\u7528\uff0c\u4e8c\u6b21\u96c7\u7528"], "eg2": [["When the simulation runs, the data for the  field gets passed through the first task so it can be used by the decision.", "\u5f53\u6a21\u62df\u8fd0\u884c\u65f6\uff0c  \u5b57\u6bb5\u7684\u6570\u636e\u5c06\u901a\u8fc7\u7b2c\u4e00\u4e2a\u4efb\u52a1\uff0c\u56e0\u6b64\u5b83\u53ef\u4ee5\u7531\u51b3\u7b56\u4f7f\u7528\u3002"], ["The company fired Nur in December 2001 -- only eight days before Ramadan ended that year -- and declared her ineligible for .", "\u8fd9\u5bb6\u79df\u8f66\u884c\u57282001\u5e7412\u6708\u2500\u2500\u8ddd\u90a3\u4e00\u5e74\u658b\u6708\u7ed3\u675f\u53ea\u6709\u516b\u5929\u65f6\u2500\u2500\u5c06\u52aa\u5c14\u89e3\u96c7\uff0c\u800c\u4e14\u5ba3\u5e03\u5979\u6ca1\u6709\u8d44\u683c\u518d\u88ab\u96c7\u7528\u3002"]], "st": {"transform": [["vt.", "rehired,rehiring"]]}}, "whomever": {"pron": {"peg": "[hu\u02d0m'ev\u0259(r)]", "pam": "[hu\u02d0m'ev\u0259(r)]"}, "wp": {"whomever I feel like": "\u516c\u53f8", "accpet whomever": "\u6ca1\u95ee\u9898", "Who suitable we selects whomever": "\u88ab\u9009\u6d3e\u7684\u4eba\u5458", "whomever r": "\u65e0\u8bba\u8c01", "I like whomever you like": "\u4f60\u559c\u6b22\u7684\u4eba", "whomever you're with": "\u65e0\u8bba\u4f60\u548c\u8c01\u5728\u4e00\u8d77", "Whomever I choose": "\u65e0\u8bba\u9009\u8c01"}, "ex": ["pron. whoever\u7684\u5bbe\u683c\uff0c\u65e0\u8bba\u8c01"], "eg2": [], "st": {}}, "cadre": {"pron": {"peg": "['k\u00e6dri]", "pam": "['k\u00e6dri]"}, "wp": {"cadre parties": "\u5e72\u90e8\u578b\u653f\u515a", "cadre school": "\u5e72\u6821", "cadet cadre": "\u519b\u6821\u5b66\u5458\u5e72\u90e8", "Cadre Trainee": "\u7cbe\u82f1\u8ba1\u5212\u50a8\u5907\u5e72\u90e8", "government cadre": "\u5e72\u90e8", "Cadre team": "\u5e72\u90e8\u961f\u4f0d", "cadre disciplines": "\u5206\u683c\u533a\u7ade\u8d5b", "Cadre Siblings": "\u5361\u5fb7\u5c14\u540c\u80de", "judicial cadre": "\u53f8\u6cd5\u5e72\u90e8"}, "ex": ["n. \u5e72\u90e8\uff1b\u57fa\u7840\u7ed3\u6784\uff1b\u9aa8\u9abc"], "eg2": [["Her mother was another loyal .", "\u5979\u7684\u6bcd\u4eb2\u4e5f\u662f\u4e2a\u5fe0\u8bda\u7684\u5e72\u90e8\u3002"], ["A  should be ready to take a lower as well as a higher post.", "\u5e72\u90e8\u8981\u80fd\u4e0a\u80fd\u4e0b\u3002"], ["After this<b> cadre</b> arrogance, our guide was forced to turn to those in the group who could speak Chinese for help.", "\u89c1\u5230\u8fd9\u4f4d\u5e72\u90e8\u7684\u50b2\u6162\u6001\u5ea6\uff0c\u6211\u4eec\u7684\u5bfc\u6e38\u53ea\u80fd\u627e\u56e2\u91cc\u80fd\u8bf4\u4e2d\u6587\u7684\u4eba\u6765\u5e2e\u5fd9\u3002"]], "st": {}}, "Civic": {"ex": ["adj. \u5e02\u7684\uff1b\u516c\u6c11\u7684\uff0c\u5e02\u6c11\u7684"], "pron": {"peg": "['s\u026av\u026ak]", "pam": "['s\u026av\u026ak]"}, "st": {}, "wp": {"Honda Civic": "\u672c\u7530\u601d\u57df;\u65b0\u601d\u57df;\u672c\u7530\u559c\u7f8e;\u672c\u7530", "Civic Exchange": "\u601d\u6c47\u653f\u7b56\u7814\u7a76\u6240;\u601d\u6c47;\u601d", "Civic Choice": "\u516c\u6c11\u9009\u62e9", "Civic Culture": "\u516c\u6c11\u6587\u5316;\u5e02\u6c11\u6587\u5316;\u6b21\u4e4b\u516c\u6c11\u7f8e\u5fb7;\u57ce\u5e02\u6587\u5316", "Civic Republicanism": "\u516c\u6c11\u5171\u548c\u4e3b\u4e49", "Civic Journalism": "\u516c\u6c11\u65b0\u95fb", "Civic Square": "\u6f14\u835f\u5e7f\u573a;\u5e02\u6c11\u5e7f\u573a;\u57ce\u5e02\u5e7f\u573a", "civic beauty": "\u57ce\u90fd\u7f8e", "civic plaza": "\u5e02\u6c11\u5e7f\u573a;\u57ce\u5e02\u5e7f\u573a;\u516c\u6c11\u5e7f\u573a"}, "eg2": [["In a study of American<b> Civic</b> virtues, gratitude must be front and center.", "\u5728\u7814\u7a76\u7f8e\u56fd\u7684\u516c\u6c11\u9053\u5fb7\u65f6\uff0c\u611f\u6069\u5fc5\u987b\u662f\u6838\u5fc3\u548c\u7b2c\u4e00\u4f4d\u7684\u3002"], ["Its members tend to be enthusiastic about the Web and enthusiastic about  participation; they are skeptical of the Internet as a panacea for politics.", "\u5176\u6210\u5458\u503e\u5411\u4e8e\u5bf9\u7f51\u7edc\u548c\u516c\u6c11\u7684\u53c2\u4e0e\u90fd\u5145\u6ee1\u70ed\u60c5\uff1b\u4ed6\u4eec\u5bf9\u4e8e\u628a\u4e92\u8054\u7f51\u4f5c\u4e3a\u89e3\u51b3\u653f\u6cbb\u95ee\u9898\u7684\u7075\u4e39\u5999\u836f\u8868\u793a\u6000\u7591\u3002"], ["Once these building blocks were in place, other aspects of modernity like democracy and<b> Civic</b> participation could be added.", "\u4e00\u65e6\u6240\u6709\u8fd9\u4e9b\u6784\u4ef6\u5230\u4f4d\uff0c\u73b0\u4ee3\u6027\u7684\u5176\u4ed6\u65b9\u9762\u6bd4\u5982\u6c11\u4e3b\u548c\u516c\u6c11\u53c2\u4e0e\u5c31\u53ef\u4ee5\u6dfb\u52a0\u4e0a\u53bb\u3002"]]}, "Warsaw": {"ex": ["n. \u534e\u6c99\uff1b\u3010\u57ce\u3011\u534e\u6c99", "\u7f51\u7edc \u6ce2\u5170\uff1b\u6ce2\u5170\u534e\u6c99\uff1b\u534e\u6c99\u5e02"], "pron": {"peg": "\u82f1\u00a0", "pam": "\u7f8e\u00a0"}, "eg2": []}, "repentant": {"pron": {"peg": "[r\u026a'p\u025bnt\u0259nt]", "pam": "[r\u026a'p\u025bnt\u0259nt]"}, "wp": {"Repentant Vampire": "\u5fcf\u6094\u51e1\u6d3e\u5c14;\u5fcf\u6094\u5438\u8840\u9b3c", "The Repentant": "\u6094\u8fc7\u7684\u5973\u4eba", "Repentant Blacksmith": "\u5fcf\u6094\u7684\u94c1\u5320", "Hard Repentant": "\u96be\u4ee5\u6094\u6539", "Be Repentant": "\u6094\u8fc7", "Angels Repentant": "\u6094\u6068\u5929\u4f7f", "not repentant": "\u4e0d\u60ed\u6127\u7684", "compunctious penitential repentant": "\u540e\u6094\u7684", "repentant consciousness": "\u5fcf\u6094\u610f\u8bc6"}, "ex": ["adj. \u6094\u6539\u7684\uff1b\u540e\u6094\u7684"], "eg2": [["He was openly<b> repentant</b> about his lack of reading skills.", "\u4ed6\u5f88\u5766\u7136\u5730\u5bf9\u81ea\u5df1\u7f3a\u4e4f\u9605\u8bfb\u6280\u80fd\u8868\u793a\u540e\u6094\u3002"], ["A<b> repentant</b> spirit is the healing balm to breaking the cycle of blame in a marital relationship.", "\u4e00\u4e2a\u5fcf\u6094\u7684\u7cbe\u795e\u662f\u79cd\u6da6\u6ed1\u6cb9\u6765\u6253\u7834\u5728\u5a5a\u59fb\u5173\u7cfb\u4e2d\u5faa\u73af\u7684\u8d23\u5907\u3002"], ["By Tara Conry Are you a<b> repentant</b> spendthrift who's thinking that all this frugality is looking pretty sexy?", "\u4f60\u662f\u5426\u662f\u4e00\u4e2a\u6709\u6240\u6094\u609f\u7684\u6325\u970d\u6d6a\u8d39\u8005\uff0c\u89c9\u5f97\u6240\u6709\u8fd9\u4e9b\u8282\u4fed\u884c\u4e3a\u770b\u8d77\u6765\u662f\u90a3\u4e48\u6709\u5438\u5f15\u529b\uff1f"]], "st": {}}, "patriot": {"pron": {"peg": "\u82f1\u00a0['pe\u026atri\u0259t] ", "pam": "\u7f8e\u00a0['pe\u026atri\u0259t] "}, "ex": ["n. \u7231\u56fd\u8005", "adj. \u6709\u7231\u56fd\u5fc3\u7684", "\u7f51\u7edc \u7231\u56fd\u4e3b\u4e49\u8005\uff1b\u535a\u5e1d\uff1b\u7231\u56fd\u8005\u5355\u4f4d"], "eg2": []}, "unreformed": {"ex": ["\u672a\u7ecf\u5b97\u6559\u6539\u9769\u7684"], "pron": {}, "st": {}, "wp": {}, "eg2": []}, "purge": {"pron": {"peg": "[p\u025dd\u0292]", "pam": "[p\u025dd\u0292]"}, "wp": {"gut purge": "\u6e05\u80a0", "blood purge": "\u6e05\u6d17\u51b2\u950b\u961f;\u50cf\u7528\u8840\u6d17\u8fc7\u4e00\u6837;\u8840\u6d17;\u5f62\u5bb9\u6781\u5176\u6b8b\u9177\u7684\u5c60\u6740", "PAPARAZZI PURGE": "\u544a\u5bc6\u8005;\u544a\u53d1\u8005", "Pixel Purge": "\u50cf\u7d20\u6e05\u9664;\u50cf\u7d20\u592a\u7a7a\u6218\u673a;\u50cf\u7d20\u51c0\u5316;\u50cf\u7d20\u626b\u8361", "The Purge": "\u4eba\u7c7b\u6e05\u9664\u8ba1\u5212;\u56fd\u5b9a\u6740\u622e\u65e5;\u5927\u6e05\u6d17;\u4eba\u7c7b\u6e05\u6d17\u8ba1\u5212", "Bloody Purge": "\u8840\u4e4b\u6d41\u653e;\u8840\u4e4b\u653e\u9010;\u8840\u8165\u51c0\u5316;\u8840\u8165\u6d41\u653e", "purge compounds": "\u6e05\u57fa\u6599", "purge date": "\u6e05\u9664\u5e74\u6708\u65e5", "furnace purge": "\u7089\u819b\u5439\u626b"}, "ex": ["vi. \u51c0\u5316\uff1b\u901a\u4fbf", "vt. \u51c0\u5316\uff1b\u6e05\u6d17\uff1b\u901a\u4fbf", "n. \u51c0\u5316\uff1b\u6cfb\u836f"], "eg2": [["The empty table is then ready to ingest new data until its next  date.", "\u7136\u540e\uff0c\u91cd\u65b0\u521b\u5efa\u7684\u7a7a\u8868\u53c8\u53ef\u4ee5\u6444\u53d6\u65b0\u7684\u6570\u636e\uff0c\u76f4\u5230\u6e05\u6d17\u65e5\u7684\u5230\u6765\u3002"], ["Your task is to build a tightly defended base and then  the planet of all infested buildings.", "\u4f60\u7684\u4efb\u52a1\u662f\u5efa\u9020\u4e00\u4e2a\u4e25\u5bc6\u9632\u5b88\u7684\u57fa\u5730\u5e76\u51c0\u5316\u884c\u661f\u4e0a\u6240\u6709\u7684\u88ab\u611f\u67d3\u5efa\u7b51\u3002"], ["I will do my best to document these<b> purge</b> trips every week, whether the stuff goes to the landfill, the recycling bin, the consignment shop or Goodwill.", "\u6bcf\u4e2a\u661f\u671f\uff0c\u6211\u90fd\u4f1a\u5c3d\u529b\u53bb\u8bb0\u5f55\u8fd9\u4e9b\u51c0\u5316\u7684\u884c\u7a0b\uff0c\u4e0d\u7ba1\u8fd9\u4e9b\u7269\u54c1\u6700\u7ec8\u662f\u88ab\u9001\u5230\u4e86\u5783\u573e\u5806\u3001\u56de\u6536\u7ad9\u3001\u6258\u8fd0\u7ad9\u6216\u662f\u4f4e\u4ef7\u56de\u6536\u7ad9\u3002"]], "st": {"transform": [["vt.", "purged,purging"]]}}}, "article": "Lacking a supermajority to amend the constitution, PiS did the next best thing and nobbled the constitutional tribunal. It replaced five judges seated by the previous parliament (including two who, admittedly, the PO had appointed irregularly when a loss at the polls looked imminent). More egregiously, the government ignored several unfavourable rulings.\n\nThe second feature of PiS-style democracy is rulers\u2019 freedom of action. The justice minister doubles as the chief prosecutor, deciding which transgressions to prosecute (Smolensk counter-protesters) and which to ignore (marchers with illegal fascist flags). A draft law would sack the entire diplomatic corps and let the foreign minister rehire whomever he wants.\n\nIn this worldview cadres are everything. According to an analysis by the Forum of Civic Development, a think-tank in Warsaw, 37 PiS laws have led to the sacking of more than 11,300 civil servants. The party decides which ex-communists are repentant patriots (PiS\u2019s ranks are full of such figures), and which are unreformed enemies of the state. Many of the latter, including military top brass, have been purged."}